{
	"id": 1,
	"width": 600,
	"height": 400,
	"name": "design_1378692277184",
	"background_fname": "black.png",
	"elements": [
		{
			"id": 1,
			"fname": "artshow1.png",
			"type": "graphic",
			"importance": 3,
			"x": 39,
			"y": 25,
			"height": 218,
			"width": 128.184,
			"group_id": -1,
			"loaded": true,
			"resizing": false,
			"fixed": false,
			"alternate": -1,
			"num_lines": 0,
			"num_alternates": -1,
			"selected": true,
			"old_text": "",
			"type_id": 2,
			"aspect_ratio": 0.588,
			"anchors": {
				"topLeft": "{\"attrs\":{\"x\":39,\"y\":243,\"fill\":\"#292\",\"opacity\":0.6,\"radius\":6,\"name\":\"topLeft\",\"draggable\":true,\"visible\":false},\"className\":\"Circle\"}",
				"topRight": "{\"attrs\":{\"x\":167.184,\"y\":243,\"fill\":\"#292\",\"opacity\":0.6,\"radius\":6,\"name\":\"topRight\",\"draggable\":true,\"visible\":false,\"rotation\":0,\"scaleX\":1,\"scaleY\":1,\"offsetX\":0,\"offsetY\":0,\"skewX\":0,\"skewY\":0},\"className\":\"Circle\"}",
				"bottomLeft": "{\"attrs\":{\"x\":39,\"y\":25,\"fill\":\"#292\",\"opacity\":0.6,\"radius\":6,\"name\":\"bottomLeft\",\"draggable\":true,\"visible\":false},\"className\":\"Circle\"}",
				"bottomRight": "{\"attrs\":{\"x\":167.184,\"y\":25,\"fill\":\"#292\",\"opacity\":0.6,\"radius\":6,\"name\":\"bottomRight\",\"draggable\":true,\"visible\":false,\"rotation\":0,\"scaleX\":1,\"scaleY\":1,\"offsetX\":0,\"offsetY\":0,\"skewX\":0,\"skewY\":0},\"className\":\"Circle\"}"
			},
			"fix_alignment": false,
			"fixed_amount": 0.9218694357169842,
			"align_type": -1,
			"fix_alternate": false,
			"alternate_id": 0,
			"curr_pos": {
				"x": 128.111083984375,
				"y": 187
			},
			"region_id": -1,
			"img": "{\"attrs\":{\"x\":39,\"y\":25,\"height\":218,\"width\":128.184,\"name\":1,\"strokeEnabled\":false,\"stroke\":\"Red\",\"strokeWidth\":3,\"draggable\":true,\"rotation\":0,\"scaleX\":1,\"scaleY\":1,\"offsetX\":0,\"offsetY\":0,\"skewX\":0,\"skewY\":0,\"opacity\":1,\"visible\":true},\"className\":\"Image\"}",
			"sugg_img": "{\"attrs\":{\"x\":39,\"y\":25,\"height\":218,\"width\":128.184,\"name\":1,\"strokeEnabled\":false,\"stroke\":\"Red\",\"strokeWidth\":3,\"draggable\":true,\"visible\":true},\"className\":\"Image\"}"
		},
		{
			"id": 2,
			"text": "Ichiro Takimura",
			"type": "text",
			"importance": 3,
			"x": 265,
			"y": 26,
			"height": 42,
			"group_id": -1,
			"bold": false,
			"italic": false,
			"align": "left",
			"font": "Garamond",
			"color": "#FF0000",
			"background_color": "#00FF00",
			"loaded": true,
			"resizing": false,
			"fixed": false,
			"alternate": -1,
			"num_lines": 1,
			"num_alternates": -1,
			"selected": false,
			"old_text": "",
			"type_id": 1,
			"sugg_align": "left",
			"alternate_imgs": {
				"left": "{\"attrs\":{\"x\":35,\"y\":138,\"width\":304.32,\"height\":48,\"strokeEnabled\":false,\"stroke\":\"Red\",\"strokeWidth\":3,\"name\":\"2\",\"draggable\":true},\"className\":\"Image\"}"
			},
			"alternate_sugg_imgs": {
				"left": "{\"attrs\":{\"x\":35,\"y\":138,\"width\":304.32,\"height\":48,\"strokeEnabled\":false,\"stroke\":\"Red\",\"strokeWidth\":3,\"name\":\"2\",\"draggable\":true},\"className\":\"Image\"}"
			},
			"anchors": {
				"topLeft": "{\"attrs\":{\"x\":265,\"y\":68,\"fill\":\"#292\",\"opacity\":0.6,\"radius\":6,\"name\":\"topLeft\",\"draggable\":true,\"visible\":false},\"className\":\"Circle\"}",
				"topRight": "{\"attrs\":{\"x\":531.28,\"y\":68,\"fill\":\"#292\",\"opacity\":0.6,\"radius\":6,\"name\":\"topRight\",\"draggable\":true,\"visible\":false},\"className\":\"Circle\"}",
				"bottomLeft": "{\"attrs\":{\"x\":265,\"y\":26,\"fill\":\"#292\",\"opacity\":0.6,\"radius\":6,\"name\":\"bottomLeft\",\"draggable\":true,\"visible\":false},\"className\":\"Circle\"}",
				"bottomRight": "{\"attrs\":{\"x\":531.28,\"y\":26,\"fill\":\"#292\",\"opacity\":0.6,\"radius\":6,\"name\":\"bottomRight\",\"draggable\":true,\"visible\":false},\"className\":\"Circle\"}"
			},
			"aspect_ratio": 6.34,
			"fix_alignment": false,
			"width": 266.28,
			"fixed_amount": 0.5199821538296836,
			"align_type": -1,
			"fix_alternate": false,
			"orig_text": "Ichiro Takimura",
			"max_line_length": 15,
			"alignment_imgs": {
				"left": "{\"attrs\":{\"x\":265,\"y\":26,\"width\":266.28,\"height\":42,\"strokeEnabled\":false,\"stroke\":\"Red\",\"strokeWidth\":3,\"name\":\"2\",\"draggable\":true,\"visible\":true,\"opacity\":1,\"rotation\":0,\"scaleX\":1,\"scaleY\":1,\"offsetX\":0,\"offsetY\":0,\"skewX\":0,\"skewY\":0},\"className\":\"Image\"}"
			},
			"alignment_sugg_imgs": {
				"left": "{\"attrs\":{\"x\":265,\"y\":26,\"width\":266.28,\"height\":42,\"strokeEnabled\":false,\"stroke\":\"Red\",\"strokeWidth\":3,\"name\":\"2\",\"draggable\":true,\"visible\":true},\"className\":\"Image\"}"
			},
			"alternate_id": 0,
			"region_id": -1,
			"curr_pos": {
				"x": 395.111083984375,
				"y": 68
			},
			"img": "{\"attrs\":{\"x\":265,\"y\":26,\"width\":266.28,\"height\":42,\"strokeEnabled\":false,\"stroke\":\"Red\",\"strokeWidth\":3,\"name\":\"2\",\"draggable\":true,\"visible\":true,\"opacity\":1,\"rotation\":0,\"scaleX\":1,\"scaleY\":1,\"offsetX\":0,\"offsetY\":0,\"skewX\":0,\"skewY\":0},\"className\":\"Image\"}",
			"sugg_img": "{\"attrs\":{\"x\":265,\"y\":26,\"width\":266.28,\"height\":42,\"strokeEnabled\":false,\"stroke\":\"Red\",\"strokeWidth\":3,\"name\":\"2\",\"draggable\":true,\"visible\":true},\"className\":\"Image\"}"
		},
		{
			"id": 3,
			"text": "Portraits",
			"type": "text",
			"importance": 3,
			"x": 39,
			"y": 323,
			"height": 43,
			"group_id": -1,
			"bold": false,
			"italic": false,
			"align": "center",
			"font": "Garamond",
			"color": "#FF0000",
			"loaded": true,
			"resizing": false,
			"fixed": false,
			"alternate": -1,
			"num_lines": 1,
			"num_alternates": -1,
			"selected": false,
			"old_text": "",
			"type_id": 1,
			"sugg_align": "center",
			"alternate_imgs": {
				"center": "{\"attrs\":{\"x\":92,\"y\":46,\"width\":187.04,\"height\":56,\"strokeEnabled\":false,\"stroke\":\"Red\",\"strokeWidth\":3,\"name\":\"3\",\"draggable\":true},\"className\":\"Image\"}"
			},
			"alternate_sugg_imgs": {
				"center": "{\"attrs\":{\"x\":92,\"y\":46,\"width\":187.04,\"height\":56,\"strokeEnabled\":false,\"stroke\":\"Red\",\"strokeWidth\":3,\"name\":\"3\",\"draggable\":true},\"className\":\"Image\"}"
			},
			"anchors": {
				"topLeft": "{\"attrs\":{\"x\":39,\"y\":366,\"fill\":\"#292\",\"opacity\":0.6,\"radius\":6,\"name\":\"topLeft\",\"draggable\":true,\"visible\":false},\"className\":\"Circle\"}",
				"topRight": "{\"attrs\":{\"x\":182.62,\"y\":366,\"fill\":\"#292\",\"opacity\":0.6,\"radius\":6,\"name\":\"topRight\",\"draggable\":true,\"visible\":false,\"rotation\":0,\"scaleX\":1,\"scaleY\":1,\"offsetX\":0,\"offsetY\":0,\"skewX\":0,\"skewY\":0},\"className\":\"Circle\"}",
				"bottomLeft": "{\"attrs\":{\"x\":39,\"y\":323,\"fill\":\"#292\",\"opacity\":0.6,\"radius\":6,\"name\":\"bottomLeft\",\"draggable\":true,\"visible\":false},\"className\":\"Circle\"}",
				"bottomRight": "{\"attrs\":{\"x\":182.62,\"y\":323,\"fill\":\"#292\",\"opacity\":0.6,\"radius\":6,\"name\":\"bottomRight\",\"draggable\":true,\"visible\":false},\"className\":\"Circle\"}"
			},
			"aspect_ratio": 3.34,
			"fix_alignment": false,
			"width": 143.62,
			"fixed_amount": 0.31465856016757393,
			"align_type": -1,
			"fix_alternate": false,
			"orig_text": "Portraits",
			"max_line_length": 9,
			"alignment_imgs": {
				"center": "{\"attrs\":{\"x\":39,\"y\":323,\"width\":143.62,\"height\":43,\"strokeEnabled\":false,\"stroke\":\"Red\",\"strokeWidth\":3,\"name\":\"3\",\"draggable\":true,\"visible\":true,\"opacity\":1,\"rotation\":0,\"scaleX\":1,\"scaleY\":1,\"offsetX\":0,\"offsetY\":0,\"skewX\":0,\"skewY\":0},\"className\":\"Image\"}"
			},
			"alignment_sugg_imgs": {
				"center": "{\"attrs\":{\"x\":33,\"y\":323,\"width\":140.28,\"height\":42,\"strokeEnabled\":false,\"stroke\":\"Red\",\"strokeWidth\":3,\"name\":\"3\",\"draggable\":true,\"visible\":true},\"className\":\"Image\"}"
			},
			"alternate_id": 0,
			"region_id": -1,
			"curr_pos": {
				"x": 179.111083984375,
				"y": 47
			},
			"img": "{\"attrs\":{\"x\":39,\"y\":323,\"width\":143.62,\"height\":43,\"strokeEnabled\":false,\"stroke\":\"Red\",\"strokeWidth\":3,\"name\":\"3\",\"draggable\":true,\"visible\":true,\"opacity\":1,\"rotation\":0,\"scaleX\":1,\"scaleY\":1,\"offsetX\":0,\"offsetY\":0,\"skewX\":0,\"skewY\":0},\"className\":\"Image\"}",
			"sugg_img": "{\"attrs\":{\"x\":33,\"y\":323,\"width\":140.28,\"height\":42,\"strokeEnabled\":false,\"stroke\":\"Red\",\"strokeWidth\":3,\"name\":\"3\",\"draggable\":true,\"visible\":true},\"className\":\"Image\"}"
		},
		{
			"loaded": true,
			"resizing": false,
			"fixed": false,
			"align_type": -1,
			"num_lines": 1,
			"selected": false,
			"old_text": "",
			"type": "text",
			"id": 7,
			"fixed_amount": 0.8359729153291425,
			"alternate_id": 0,
			"x": 228,
			"y": 89,
			"group_id": "-1",
			"importance": "2",
			"type_id": 1,
			"font": "Garamond",
			"bold": false,
			"italic": false,
			"fix_alignment": false,
			"fix_alternate": false,
			"color": "FF0000",
			"text": "Winner of the Killan Prize",
			"align": "center",
			"sugg_align": "left",
			"height": 33,
			"orig_text": "Winner of the\nKillan Prize",
			"max_line_length": 26,
			"alignment_imgs": {
				"left": "{\"attrs\":{\"x\":228,\"y\":89,\"width\":339.90000000000003,\"height\":33,\"strokeEnabled\":false,\"stroke\":\"Red\",\"strokeWidth\":3,\"name\":\"7\",\"draggable\":true,\"visible\":true,\"opacity\":1,\"rotation\":0,\"scaleX\":1,\"scaleY\":1,\"offsetX\":0,\"offsetY\":0,\"skewX\":0,\"skewY\":0},\"className\":\"Image\"}"
			},
			"alignment_sugg_imgs": {
				"left": "{\"attrs\":{\"x\":222,\"y\":89,\"width\":350.20000000000005,\"height\":34,\"strokeEnabled\":false,\"stroke\":\"Red\",\"strokeWidth\":3,\"name\":\"7\",\"draggable\":true,\"visible\":true},\"className\":\"Image\"}"
			},
			"anchors": {
				"topLeft": "{\"attrs\":{\"x\":228,\"y\":122,\"fill\":\"#292\",\"opacity\":0.6,\"radius\":6,\"name\":\"topLeft\",\"draggable\":true,\"visible\":false},\"className\":\"Circle\"}",
				"topRight": "{\"attrs\":{\"x\":567.9000000000001,\"y\":122,\"fill\":\"#292\",\"opacity\":0.6,\"radius\":6,\"name\":\"topRight\",\"draggable\":true,\"visible\":false},\"className\":\"Circle\"}",
				"bottomLeft": "{\"attrs\":{\"x\":228,\"y\":89,\"fill\":\"#292\",\"opacity\":0.6,\"radius\":6,\"name\":\"bottomLeft\",\"draggable\":true,\"visible\":false},\"className\":\"Circle\"}",
				"bottomRight": "{\"attrs\":{\"x\":567.9000000000001,\"y\":89,\"fill\":\"#292\",\"opacity\":0.6,\"radius\":6,\"name\":\"bottomRight\",\"draggable\":true,\"visible\":false},\"className\":\"Circle\"}"
			},
			"aspect_ratio": 10.3,
			"curr_pos": {
				"x": 388.111083984375,
				"y": 107
			},
			"width": 339.90000000000003,
			"region_id": -1,
			"img": "{\"attrs\":{\"x\":228,\"y\":89,\"width\":339.90000000000003,\"height\":33,\"strokeEnabled\":false,\"stroke\":\"Red\",\"strokeWidth\":3,\"name\":\"7\",\"draggable\":true,\"visible\":true,\"opacity\":1,\"rotation\":0,\"scaleX\":1,\"scaleY\":1,\"offsetX\":0,\"offsetY\":0,\"skewX\":0,\"skewY\":0},\"className\":\"Image\"}",
			"sugg_img": "{\"attrs\":{\"x\":222,\"y\":89,\"width\":350.20000000000005,\"height\":34,\"strokeEnabled\":false,\"stroke\":\"Red\",\"strokeWidth\":3,\"name\":\"7\",\"draggable\":true,\"visible\":true},\"className\":\"Image\"}"
		},
		{
			"id": 4,
			"text": "July 21 -\nAugust 10, 2011",
			"type": "text",
			"importance": 1,
			"x": 365,
			"y": 186,
			"height": 57,
			"group_id": -1,
			"bold": false,
			"italic": false,
			"align": "center",
			"font": "Garamond",
			"color": "#FFFFFF",
			"loaded": true,
			"resizing": false,
			"fixed": false,
			"alternate": -1,
			"num_lines": 2,
			"num_alternates": -1,
			"selected": false,
			"old_text": "",
			"type_id": 1,
			"sugg_align": "center",
			"alternate_imgs": {
				"center": "{\"attrs\":{\"x\":35,\"y\":214,\"width\":301.32,\"height\":31,\"strokeEnabled\":false,\"stroke\":\"Red\",\"strokeWidth\":3,\"name\":\"4\",\"draggable\":true},\"className\":\"Image\"}"
			},
			"alternate_sugg_imgs": {
				"center": "{\"attrs\":{\"x\":35,\"y\":214,\"width\":301.32,\"height\":31,\"strokeEnabled\":false,\"stroke\":\"Red\",\"strokeWidth\":3,\"name\":\"4\",\"draggable\":true},\"className\":\"Image\"}"
			},
			"anchors": {
				"topLeft": "{\"attrs\":{\"x\":365,\"y\":243,\"fill\":\"#292\",\"opacity\":0.6,\"radius\":6,\"name\":\"topLeft\",\"draggable\":true,\"visible\":false},\"className\":\"Circle\"}",
				"topRight": "{\"attrs\":{\"x\":545.5,\"y\":243,\"fill\":\"#292\",\"opacity\":0.6,\"radius\":6,\"name\":\"topRight\",\"draggable\":true,\"visible\":false},\"className\":\"Circle\"}",
				"bottomLeft": "{\"attrs\":{\"x\":365,\"y\":186,\"fill\":\"#292\",\"opacity\":0.6,\"radius\":6,\"name\":\"bottomLeft\",\"draggable\":true,\"visible\":false},\"className\":\"Circle\"}",
				"bottomRight": "{\"attrs\":{\"x\":545.5,\"y\":186,\"fill\":\"#292\",\"opacity\":0.6,\"radius\":6,\"name\":\"bottomRight\",\"draggable\":true,\"visible\":false},\"className\":\"Circle\"}"
			},
			"aspect_ratio": 3.1666666666666665,
			"fix_alignment": false,
			"width": 180.5,
			"fixed_amount": 0.0010061068335538998,
			"align_type": 1,
			"fix_alternate": false,
			"orig_text": "July 21 -\nAugust 10, 2011",
			"max_line_length": 15,
			"alignment_imgs": {
				"left": "{\"attrs\":{\"x\":392,\"y\":199,\"width\":193.16666666666666,\"height\":61,\"strokeEnabled\":false,\"stroke\":\"Red\",\"strokeWidth\":3,\"name\":\"4\",\"draggable\":true,\"visible\":true,\"opacity\":1},\"className\":\"Image\"}",
				"center": "{\"attrs\":{\"x\":365,\"y\":186,\"width\":180.5,\"height\":57,\"strokeEnabled\":false,\"stroke\":\"Red\",\"strokeWidth\":3,\"name\":\"4\",\"draggable\":true,\"visible\":true,\"opacity\":1},\"className\":\"Image\"}",
				"right": "{\"attrs\":{\"x\":24,\"y\":313,\"width\":167.83333333333331,\"height\":53,\"strokeEnabled\":false,\"stroke\":\"Red\",\"strokeWidth\":3,\"name\":\"4\",\"draggable\":true,\"visible\":false},\"className\":\"Image\"}"
			},
			"alignment_sugg_imgs": {
				"left": "{\"attrs\":{\"x\":392,\"y\":199,\"width\":193.16666666666666,\"height\":61,\"strokeEnabled\":false,\"stroke\":\"Red\",\"strokeWidth\":3,\"name\":\"4\",\"draggable\":true,\"visible\":true},\"className\":\"Image\"}",
				"center": "{\"attrs\":{\"x\":367,\"y\":185,\"width\":180.5,\"height\":57,\"strokeEnabled\":false,\"stroke\":\"Red\",\"strokeWidth\":3,\"name\":\"4\",\"draggable\":true,\"visible\":true},\"className\":\"Image\"}",
				"right": "{\"attrs\":{\"x\":24,\"y\":313,\"width\":167.83333333333331,\"height\":53,\"strokeEnabled\":false,\"stroke\":\"Red\",\"strokeWidth\":3,\"name\":\"4\",\"draggable\":true,\"visible\":false},\"className\":\"Image\"}"
			},
			"alternate_id": 1,
			"region_id": -1,
			"curr_pos": {
				"x": 114.44442749023438,
				"y": 352
			},
			"img": "{\"attrs\":{\"x\":365,\"y\":186,\"width\":180.5,\"height\":57,\"strokeEnabled\":false,\"stroke\":\"Red\",\"strokeWidth\":3,\"name\":\"4\",\"draggable\":true,\"visible\":true,\"opacity\":1},\"className\":\"Image\"}",
			"sugg_img": "{\"attrs\":{\"x\":367,\"y\":185,\"width\":180.5,\"height\":57,\"strokeEnabled\":false,\"stroke\":\"Red\",\"strokeWidth\":3,\"name\":\"4\",\"draggable\":true,\"visible\":true},\"className\":\"Image\"}"
		},
		{
			"id": 5,
			"text": "Gallery 81\n812 Spadina Ave\nToronto",
			"type": "text",
			"importance": 0,
			"x": 394,
			"y": 311,
			"height": 56,
			"bold": false,
			"italic": false,
			"group_id": -1,
			"align": "center",
			"font": "Garamond",
			"color": "#FFFFFF",
			"loaded": true,
			"resizing": false,
			"fixed": false,
			"alternate": -1,
			"num_lines": 3,
			"num_alternates": 3,
			"selected": false,
			"old_text": "",
			"type_id": 1,
			"sugg_align": "center",
			"alternate_imgs": {
				"left": "{\"attrs\":{\"x\":92,\"y\":271,\"width\":186.74285714285713,\"height\":86,\"strokeEnabled\":false,\"stroke\":\"Red\",\"strokeWidth\":3,\"name\":\"5\",\"draggable\":true},\"className\":\"Image\"}",
				"center": "{\"attrs\":{\"x\":96,\"y\":273,\"width\":180.22857142857143,\"height\":83,\"strokeEnabled\":false,\"stroke\":\"Red\",\"strokeWidth\":3,\"name\":\"5\",\"draggable\":true},\"className\":\"Image\"}",
				"right": "{\"attrs\":{\"x\":92,\"y\":271,\"width\":186.74285714285713,\"height\":86,\"strokeEnabled\":false,\"stroke\":\"Red\",\"strokeWidth\":3,\"name\":\"5\",\"draggable\":true},\"className\":\"Image\"}"
			},
			"alternate_sugg_imgs": {
				"left": "{\"attrs\":{\"x\":92,\"y\":271,\"width\":186.74285714285713,\"height\":86,\"strokeEnabled\":false,\"stroke\":\"Red\",\"strokeWidth\":3,\"name\":\"5\",\"draggable\":true},\"className\":\"Image\"}",
				"center": "{\"attrs\":{\"x\":96,\"y\":273,\"width\":180.22857142857143,\"height\":83,\"strokeEnabled\":false,\"stroke\":\"Red\",\"strokeWidth\":3,\"name\":\"5\",\"draggable\":true},\"className\":\"Image\"}",
				"right": "{\"attrs\":{\"x\":92,\"y\":271,\"width\":186.74285714285713,\"height\":86,\"strokeEnabled\":false,\"stroke\":\"Red\",\"strokeWidth\":3,\"name\":\"5\",\"draggable\":true},\"className\":\"Image\"}"
			},
			"anchors": {
				"topLeft": "{\"attrs\":{\"x\":394,\"y\":367,\"fill\":\"#292\",\"opacity\":0.6,\"radius\":6,\"name\":\"topLeft\",\"draggable\":true,\"visible\":false},\"className\":\"Circle\"}",
				"topRight": "{\"attrs\":{\"x\":515.6,\"y\":367,\"fill\":\"#292\",\"opacity\":0.6,\"radius\":6,\"name\":\"topRight\",\"draggable\":true,\"visible\":false},\"className\":\"Circle\"}",
				"bottomLeft": "{\"attrs\":{\"x\":394,\"y\":311,\"fill\":\"#292\",\"opacity\":0.6,\"radius\":6,\"name\":\"bottomLeft\",\"draggable\":true,\"visible\":false},\"className\":\"Circle\"}",
				"bottomRight": "{\"attrs\":{\"x\":515.6,\"y\":311,\"fill\":\"#292\",\"opacity\":0.6,\"radius\":6,\"name\":\"bottomRight\",\"draggable\":true,\"visible\":false},\"className\":\"Circle\"}"
			},
			"aspect_ratio": 2.1714285714285713,
			"fix_alignment": false,
			"width": 121.6,
			"fixed_amount": 0.6961227826125412,
			"align_type": 1,
			"fix_alternate": false,
			"orig_text": "Gallery 81\n812 Spadina Ave\nToronto",
			"max_line_length": 15,
			"alignment_imgs": {
				"left": "{\"attrs\":{\"x\":392,\"y\":304,\"width\":134.6285714285714,\"height\":62,\"strokeEnabled\":false,\"stroke\":\"Red\",\"strokeWidth\":3,\"name\":\"5\",\"draggable\":true,\"visible\":true,\"opacity\":1},\"className\":\"Image\"}",
				"center": "{\"attrs\":{\"x\":394,\"y\":311,\"width\":121.6,\"height\":56,\"strokeEnabled\":false,\"stroke\":\"Red\",\"strokeWidth\":3,\"name\":\"5\",\"draggable\":true,\"visible\":true,\"opacity\":1,\"rotation\":0,\"scaleX\":1,\"scaleY\":1,\"offsetX\":0,\"offsetY\":0,\"skewX\":0,\"skewY\":0},\"className\":\"Image\"}",
				"right": "{\"attrs\":{\"x\":209,\"y\":301,\"width\":152,\"height\":70,\"strokeEnabled\":false,\"stroke\":\"Red\",\"strokeWidth\":3,\"name\":\"5\",\"draggable\":true,\"visible\":false},\"className\":\"Image\"}"
			},
			"alignment_sugg_imgs": {
				"left": "{\"attrs\":{\"x\":392,\"y\":304,\"width\":134.6285714285714,\"height\":62,\"strokeEnabled\":false,\"stroke\":\"Red\",\"strokeWidth\":3,\"name\":\"5\",\"draggable\":true,\"visible\":true},\"className\":\"Image\"}",
				"center": "{\"attrs\":{\"x\":394,\"y\":309,\"width\":123.77142857142856,\"height\":57,\"strokeEnabled\":false,\"stroke\":\"Red\",\"strokeWidth\":3,\"name\":\"5\",\"draggable\":true,\"visible\":true},\"className\":\"Image\"}",
				"right": "{\"attrs\":{\"x\":209,\"y\":301,\"width\":152,\"height\":70,\"strokeEnabled\":false,\"stroke\":\"Red\",\"strokeWidth\":3,\"name\":\"5\",\"draggable\":true,\"visible\":false},\"className\":\"Image\"}"
			},
			"alternate_id": 2,
			"region_id": -1,
			"curr_pos": {
				"x": 449.111083984375,
				"y": 338
			},
			"img": "{\"attrs\":{\"x\":394,\"y\":311,\"width\":121.6,\"height\":56,\"strokeEnabled\":false,\"stroke\":\"Red\",\"strokeWidth\":3,\"name\":\"5\",\"draggable\":true,\"visible\":true,\"opacity\":1,\"rotation\":0,\"scaleX\":1,\"scaleY\":1,\"offsetX\":0,\"offsetY\":0,\"skewX\":0,\"skewY\":0},\"className\":\"Image\"}",
			"sugg_img": "{\"attrs\":{\"x\":394,\"y\":309,\"width\":123.77142857142856,\"height\":57,\"strokeEnabled\":false,\"stroke\":\"Red\",\"strokeWidth\":3,\"name\":\"5\",\"draggable\":true,\"visible\":true},\"className\":\"Image\"}"
		},
		{
			"loaded": true,
			"resizing": false,
			"fixed": false,
			"align_type": -1,
			"num_lines": 0,
			"selected": false,
			"old_text": "",
			"type": "graphic",
			"id": 6,
			"fixed_amount": 0.8062537499300206,
			"alternate_id": 0,
			"x": 194,
			"y": 149,
			"fname": "graphic2.png",
			"group_id": "-1",
			"importance": "0",
			"type_id": 2,
			"height": 217,
			"aspect_ratio": 0.6640625,
			"anchors": {
				"topLeft": "{\"attrs\":{\"x\":194,\"y\":366,\"fill\":\"#292\",\"opacity\":0.6,\"radius\":6,\"name\":\"topLeft\",\"draggable\":true,\"visible\":false},\"className\":\"Circle\"}",
				"topRight": "{\"attrs\":{\"x\":338.1015625,\"y\":366,\"fill\":\"#292\",\"opacity\":0.6,\"radius\":6,\"name\":\"topRight\",\"draggable\":true,\"visible\":false,\"rotation\":0,\"scaleX\":1,\"scaleY\":1,\"offsetX\":0,\"offsetY\":0,\"skewX\":0,\"skewY\":0},\"className\":\"Circle\"}",
				"bottomLeft": "{\"attrs\":{\"x\":194,\"y\":149,\"fill\":\"#292\",\"opacity\":0.6,\"radius\":6,\"name\":\"bottomLeft\",\"draggable\":true,\"visible\":false},\"className\":\"Circle\"}",
				"bottomRight": "{\"attrs\":{\"x\":338.1015625,\"y\":149,\"fill\":\"#292\",\"opacity\":0.6,\"radius\":6,\"name\":\"bottomRight\",\"draggable\":true,\"visible\":false,\"rotation\":0,\"scaleX\":1,\"scaleY\":1,\"offsetX\":0,\"offsetY\":0,\"skewX\":0,\"skewY\":0},\"className\":\"Circle\"}"
			},
			"curr_pos": {
				"x": 273.111083984375,
				"y": 274
			},
			"fix_alignment": false,
			"fix_alternate": false,
			"width": 144.1015625,
			"region_id": -1,
			"img": "{\"attrs\":{\"x\":194,\"y\":149,\"height\":217,\"width\":144.1015625,\"name\":6,\"strokeEnabled\":false,\"stroke\":\"Red\",\"strokeWidth\":3,\"draggable\":true,\"opacity\":1,\"rotation\":0,\"scaleX\":1,\"scaleY\":1,\"offsetX\":0,\"offsetY\":0,\"skewX\":0,\"skewY\":0,\"visible\":true},\"className\":\"Image\"}",
			"sugg_img": "{\"attrs\":{\"x\":194,\"y\":149,\"height\":217,\"width\":144.1015625,\"name\":6,\"strokeEnabled\":false,\"stroke\":\"Red\",\"strokeWidth\":3,\"draggable\":true,\"visible\":true},\"className\":\"Image\"}"
		}
	],
	"background": "{\"attrs\":{\"x\":0,\"y\":0,\"width\":600,\"height\":400,\"name\":\"background\",\"strokeEnabled\":true},\"className\":\"Rect\"}",
	"sugg_background": "{\"attrs\":{\"x\":0,\"y\":0,\"width\":600,\"height\":400},\"className\":\"Rect\"}",
	"overlap_regions": [
		{
			"elem_id": 1,
			"x_min": 0,
			"y_min": 0,
			"x_max": 1,
			"y_max": 1
		},
		{
			"elem_id": 6,
			"x_min": 0,
			"y_min": 0,
			"x_max": 1,
			"y_max": 1
		}
	],
	"background_elem": {
		"id": "0",
		"type": "background",
		"text": "",
		"font": "Garamond",
		"color": "#000",
		"group_id": 0,
		"importance": 0,
		"anchors": [],
		"loaded": false,
		"resizing": false,
		"selected": true,
		"bold": false,
		"italic": false,
		"align": "center",
		"x": 0,
		"y": 0,
		"img": "{\"attrs\":{\"x\":0,\"y\":0,\"width\":600,\"height\":400,\"name\":\"background\",\"strokeEnabled\":true},\"className\":\"Rect\"}",
		"curr_pos": {
			"x": 427.111083984375,
			"y": 158
		}
	},
	"regions": [],
	"element_alts": {
		"2": {
			"1": {
				"id": 2,
				"text": "Ichiro Takimura",
				"type": "text",
				"importance": 3,
				"x": 265,
				"y": 26,
				"height": 42,
				"group_id": -1,
				"bold": false,
				"italic": false,
				"align": "left",
				"font": "Garamond",
				"color": "#FF0000",
				"background_color": "#00FF00",
				"loaded": true,
				"resizing": false,
				"fixed": false,
				"alternate": -1,
				"num_lines": 1,
				"num_alternates": -1,
				"selected": false,
				"old_text": "",
				"type_id": 1,
				"sugg_align": "left",
				"alternate_imgs": {
					"left": "{\"attrs\":{\"x\":35,\"y\":138,\"width\":304.32,\"height\":48,\"strokeEnabled\":false,\"stroke\":\"Red\",\"strokeWidth\":3,\"name\":\"2\",\"draggable\":true},\"className\":\"Image\"}"
				},
				"alternate_sugg_imgs": {
					"left": "{\"attrs\":{\"x\":35,\"y\":138,\"width\":304.32,\"height\":48,\"strokeEnabled\":false,\"stroke\":\"Red\",\"strokeWidth\":3,\"name\":\"2\",\"draggable\":true},\"className\":\"Image\"}"
				},
				"anchors": {
					"topLeft": "{\"attrs\":{\"x\":265,\"y\":68,\"fill\":\"#292\",\"opacity\":0.6,\"radius\":6,\"name\":\"topLeft\",\"draggable\":true,\"visible\":false},\"className\":\"Circle\"}",
					"topRight": "{\"attrs\":{\"x\":531.28,\"y\":68,\"fill\":\"#292\",\"opacity\":0.6,\"radius\":6,\"name\":\"topRight\",\"draggable\":true,\"visible\":false},\"className\":\"Circle\"}",
					"bottomLeft": "{\"attrs\":{\"x\":265,\"y\":26,\"fill\":\"#292\",\"opacity\":0.6,\"radius\":6,\"name\":\"bottomLeft\",\"draggable\":true,\"visible\":false},\"className\":\"Circle\"}",
					"bottomRight": "{\"attrs\":{\"x\":531.28,\"y\":26,\"fill\":\"#292\",\"opacity\":0.6,\"radius\":6,\"name\":\"bottomRight\",\"draggable\":true,\"visible\":false},\"className\":\"Circle\"}"
				},
				"aspect_ratio": 6.34,
				"fix_alignment": false,
				"width": 266.28,
				"fixed_amount": 0.5199821538296836,
				"align_type": -1,
				"fix_alternate": false,
				"orig_text": "Ichiro Takimura",
				"max_line_length": 15,
				"alignment_imgs": {
					"left": "{\"attrs\":{\"x\":265,\"y\":26,\"width\":266.28,\"height\":42,\"strokeEnabled\":false,\"stroke\":\"Red\",\"strokeWidth\":3,\"name\":\"2\",\"draggable\":true,\"visible\":true,\"opacity\":1,\"rotation\":0,\"scaleX\":1,\"scaleY\":1,\"offsetX\":0,\"offsetY\":0,\"skewX\":0,\"skewY\":0},\"className\":\"Image\"}"
				},
				"alignment_sugg_imgs": {
					"left": "{\"attrs\":{\"x\":265,\"y\":26,\"width\":266.28,\"height\":42,\"strokeEnabled\":false,\"stroke\":\"Red\",\"strokeWidth\":3,\"name\":\"2\",\"draggable\":true,\"visible\":true},\"className\":\"Image\"}"
				},
				"alternate_id": 0,
				"region_id": -1,
				"curr_pos": {
					"x": 395.111083984375,
					"y": 68
				},
				"img": "{\"attrs\":{\"x\":265,\"y\":26,\"width\":266.28,\"height\":42,\"strokeEnabled\":false,\"stroke\":\"Red\",\"strokeWidth\":3,\"name\":\"2\",\"draggable\":true,\"visible\":true,\"opacity\":1,\"rotation\":0,\"scaleX\":1,\"scaleY\":1,\"offsetX\":0,\"offsetY\":0,\"skewX\":0,\"skewY\":0},\"className\":\"Image\"}",
				"sugg_img": "{\"attrs\":{\"x\":265,\"y\":26,\"width\":266.28,\"height\":42,\"strokeEnabled\":false,\"stroke\":\"Red\",\"strokeWidth\":3,\"name\":\"2\",\"draggable\":true,\"visible\":true},\"className\":\"Image\"}"
			}
		},
		"3": {
			"1": {
				"id": 3,
				"text": "Portraits",
				"type": "text",
				"importance": 3,
				"x": 39,
				"y": 323,
				"height": 43,
				"group_id": -1,
				"bold": false,
				"italic": false,
				"align": "center",
				"font": "Garamond",
				"color": "#FF0000",
				"loaded": true,
				"resizing": false,
				"fixed": false,
				"alternate": -1,
				"num_lines": 1,
				"num_alternates": -1,
				"selected": false,
				"old_text": "",
				"type_id": 1,
				"sugg_align": "center",
				"alternate_imgs": {
					"center": "{\"attrs\":{\"x\":92,\"y\":46,\"width\":187.04,\"height\":56,\"strokeEnabled\":false,\"stroke\":\"Red\",\"strokeWidth\":3,\"name\":\"3\",\"draggable\":true},\"className\":\"Image\"}"
				},
				"alternate_sugg_imgs": {
					"center": "{\"attrs\":{\"x\":92,\"y\":46,\"width\":187.04,\"height\":56,\"strokeEnabled\":false,\"stroke\":\"Red\",\"strokeWidth\":3,\"name\":\"3\",\"draggable\":true},\"className\":\"Image\"}"
				},
				"anchors": {
					"topLeft": "{\"attrs\":{\"x\":39,\"y\":366,\"fill\":\"#292\",\"opacity\":0.6,\"radius\":6,\"name\":\"topLeft\",\"draggable\":true,\"visible\":false},\"className\":\"Circle\"}",
					"topRight": "{\"attrs\":{\"x\":182.62,\"y\":366,\"fill\":\"#292\",\"opacity\":0.6,\"radius\":6,\"name\":\"topRight\",\"draggable\":true,\"visible\":false,\"rotation\":0,\"scaleX\":1,\"scaleY\":1,\"offsetX\":0,\"offsetY\":0,\"skewX\":0,\"skewY\":0},\"className\":\"Circle\"}",
					"bottomLeft": "{\"attrs\":{\"x\":39,\"y\":323,\"fill\":\"#292\",\"opacity\":0.6,\"radius\":6,\"name\":\"bottomLeft\",\"draggable\":true,\"visible\":false},\"className\":\"Circle\"}",
					"bottomRight": "{\"attrs\":{\"x\":182.62,\"y\":323,\"fill\":\"#292\",\"opacity\":0.6,\"radius\":6,\"name\":\"bottomRight\",\"draggable\":true,\"visible\":false},\"className\":\"Circle\"}"
				},
				"aspect_ratio": 3.34,
				"fix_alignment": false,
				"width": 143.62,
				"fixed_amount": 0.31465856016757393,
				"align_type": -1,
				"fix_alternate": false,
				"orig_text": "Portraits",
				"max_line_length": 9,
				"alignment_imgs": {
					"center": "{\"attrs\":{\"x\":39,\"y\":323,\"width\":143.62,\"height\":43,\"strokeEnabled\":false,\"stroke\":\"Red\",\"strokeWidth\":3,\"name\":\"3\",\"draggable\":true,\"visible\":true,\"opacity\":1,\"rotation\":0,\"scaleX\":1,\"scaleY\":1,\"offsetX\":0,\"offsetY\":0,\"skewX\":0,\"skewY\":0},\"className\":\"Image\"}"
				},
				"alignment_sugg_imgs": {
					"center": "{\"attrs\":{\"x\":33,\"y\":323,\"width\":140.28,\"height\":42,\"strokeEnabled\":false,\"stroke\":\"Red\",\"strokeWidth\":3,\"name\":\"3\",\"draggable\":true,\"visible\":true},\"className\":\"Image\"}"
				},
				"alternate_id": 0,
				"region_id": -1,
				"curr_pos": {
					"x": 179.111083984375,
					"y": 47
				},
				"img": "{\"attrs\":{\"x\":39,\"y\":323,\"width\":143.62,\"height\":43,\"strokeEnabled\":false,\"stroke\":\"Red\",\"strokeWidth\":3,\"name\":\"3\",\"draggable\":true,\"visible\":true,\"opacity\":1,\"rotation\":0,\"scaleX\":1,\"scaleY\":1,\"offsetX\":0,\"offsetY\":0,\"skewX\":0,\"skewY\":0},\"className\":\"Image\"}",
				"sugg_img": "{\"attrs\":{\"x\":33,\"y\":323,\"width\":140.28,\"height\":42,\"strokeEnabled\":false,\"stroke\":\"Red\",\"strokeWidth\":3,\"name\":\"3\",\"draggable\":true,\"visible\":true},\"className\":\"Image\"}"
			}
		},
		"4": {
			"1": {
				"id": 4,
				"text": "July 21 - August 10, 2011",
				"type": "text",
				"importance": 1,
				"x": 24,
				"y": 313,
				"height": 53,
				"group_id": -1,
				"bold": false,
				"italic": false,
				"align": "left",
				"font": "Garamond",
				"color": "#FFFFFF",
				"loaded": true,
				"resizing": false,
				"fixed": false,
				"alternate": -1,
				"num_lines": 1,
				"num_alternates": -1,
				"selected": false,
				"old_text": "",
				"type_id": 1,
				"sugg_align": "left",
				"alternate_imgs": {
					"center": "{\"attrs\":{\"x\":35,\"y\":214,\"width\":301.32,\"height\":31,\"strokeEnabled\":false,\"stroke\":\"Red\",\"strokeWidth\":3,\"name\":\"4\",\"draggable\":true},\"className\":\"Image\"}"
				},
				"alternate_sugg_imgs": {
					"center": "{\"attrs\":{\"x\":35,\"y\":214,\"width\":301.32,\"height\":31,\"strokeEnabled\":false,\"stroke\":\"Red\",\"strokeWidth\":3,\"name\":\"4\",\"draggable\":true},\"className\":\"Image\"}"
				},
				"anchors": {
					"topLeft": "{\"attrs\":{\"x\":0,\"y\":0,\"fill\":\"#292\",\"opacity\":0.6,\"radius\":6,\"name\":\"topLeft\",\"draggable\":true,\"visible\":false},\"className\":\"Circle\"}",
					"topRight": "{\"attrs\":{\"x\":0,\"y\":0,\"fill\":\"#292\",\"opacity\":0.6,\"radius\":6,\"name\":\"topRight\",\"draggable\":true,\"visible\":false},\"className\":\"Circle\"}",
					"bottomLeft": "{\"attrs\":{\"x\":0,\"y\":0,\"fill\":\"#292\",\"opacity\":0.6,\"radius\":6,\"name\":\"bottomLeft\",\"draggable\":true,\"visible\":false},\"className\":\"Circle\"}",
					"bottomRight": "{\"attrs\":{\"x\":0,\"y\":0,\"fill\":\"#292\",\"opacity\":0.6,\"radius\":6,\"name\":\"bottomRight\",\"draggable\":true,\"visible\":false},\"className\":\"Circle\"}"
				},
				"aspect_ratio": 9.72,
				"fix_alignment": false,
				"width": 167.83333333333331,
				"fixed_amount": 0.25,
				"align_type": -1,
				"fix_alternate": false,
				"orig_text": "July 21 -\nAugust 10, 2011",
				"max_line_length": 25,
				"alignment_imgs": {
					"left": "{\"attrs\":{\"x\":24,\"y\":313,\"width\":515.1600000000001,\"height\":53,\"strokeEnabled\":false,\"stroke\":\"Red\",\"strokeWidth\":3,\"name\":\"4\",\"draggable\":true,\"visible\":false},\"className\":\"Image\"}"
				},
				"alignment_sugg_imgs": {
					"left": "{\"attrs\":{\"x\":24,\"y\":313,\"width\":515.1600000000001,\"height\":53,\"strokeEnabled\":false,\"stroke\":\"Red\",\"strokeWidth\":3,\"name\":\"4\",\"draggable\":true,\"visible\":false},\"className\":\"Image\"}"
				},
				"alternate_id": 0,
				"region_id": -1,
				"curr_pos": {
					"x": 114.44442749023438,
					"y": 352
				},
				"img": "{\"attrs\":{\"x\":24,\"y\":313,\"width\":515.1600000000001,\"height\":53,\"strokeEnabled\":false,\"stroke\":\"Red\",\"strokeWidth\":3,\"name\":\"4\",\"draggable\":true,\"visible\":false},\"className\":\"Image\"}",
				"sugg_img": "{\"attrs\":{\"x\":24,\"y\":313,\"width\":515.1600000000001,\"height\":53,\"strokeEnabled\":false,\"stroke\":\"Red\",\"strokeWidth\":3,\"name\":\"4\",\"draggable\":true,\"visible\":false},\"className\":\"Image\"}"
			},
			"2": {
				"id": 4,
				"text": "July 21 -\nAugust 10, 2011",
				"type": "text",
				"importance": 1,
				"x": 365,
				"y": 186,
				"height": 57,
				"group_id": -1,
				"bold": false,
				"italic": false,
				"align": "center",
				"font": "Garamond",
				"color": "#FFFFFF",
				"loaded": true,
				"resizing": false,
				"fixed": false,
				"alternate": -1,
				"num_lines": 2,
				"num_alternates": -1,
				"selected": false,
				"old_text": "",
				"type_id": 1,
				"sugg_align": "center",
				"alternate_imgs": {
					"center": "{\"attrs\":{\"x\":35,\"y\":214,\"width\":301.32,\"height\":31,\"strokeEnabled\":false,\"stroke\":\"Red\",\"strokeWidth\":3,\"name\":\"4\",\"draggable\":true},\"className\":\"Image\"}"
				},
				"alternate_sugg_imgs": {
					"center": "{\"attrs\":{\"x\":35,\"y\":214,\"width\":301.32,\"height\":31,\"strokeEnabled\":false,\"stroke\":\"Red\",\"strokeWidth\":3,\"name\":\"4\",\"draggable\":true},\"className\":\"Image\"}"
				},
				"anchors": {
					"topLeft": "{\"attrs\":{\"x\":365,\"y\":243,\"fill\":\"#292\",\"opacity\":0.6,\"radius\":6,\"name\":\"topLeft\",\"draggable\":true,\"visible\":false},\"className\":\"Circle\"}",
					"topRight": "{\"attrs\":{\"x\":545.5,\"y\":243,\"fill\":\"#292\",\"opacity\":0.6,\"radius\":6,\"name\":\"topRight\",\"draggable\":true,\"visible\":false},\"className\":\"Circle\"}",
					"bottomLeft": "{\"attrs\":{\"x\":365,\"y\":186,\"fill\":\"#292\",\"opacity\":0.6,\"radius\":6,\"name\":\"bottomLeft\",\"draggable\":true,\"visible\":false},\"className\":\"Circle\"}",
					"bottomRight": "{\"attrs\":{\"x\":545.5,\"y\":186,\"fill\":\"#292\",\"opacity\":0.6,\"radius\":6,\"name\":\"bottomRight\",\"draggable\":true,\"visible\":false},\"className\":\"Circle\"}"
				},
				"aspect_ratio": 3.1666666666666665,
				"fix_alignment": false,
				"width": 180.5,
				"fixed_amount": 0.0010061068335538998,
				"align_type": 1,
				"fix_alternate": false,
				"orig_text": "July 21 -\nAugust 10, 2011",
				"max_line_length": 15,
				"alignment_imgs": {
					"left": "{\"attrs\":{\"x\":392,\"y\":199,\"width\":193.16666666666666,\"height\":61,\"strokeEnabled\":false,\"stroke\":\"Red\",\"strokeWidth\":3,\"name\":\"4\",\"draggable\":true,\"visible\":true,\"opacity\":1},\"className\":\"Image\"}",
					"center": "{\"attrs\":{\"x\":365,\"y\":186,\"width\":180.5,\"height\":57,\"strokeEnabled\":false,\"stroke\":\"Red\",\"strokeWidth\":3,\"name\":\"4\",\"draggable\":true,\"visible\":true,\"opacity\":1},\"className\":\"Image\"}",
					"right": "{\"attrs\":{\"x\":24,\"y\":313,\"width\":167.83333333333331,\"height\":53,\"strokeEnabled\":false,\"stroke\":\"Red\",\"strokeWidth\":3,\"name\":\"4\",\"draggable\":true,\"visible\":false},\"className\":\"Image\"}"
				},
				"alignment_sugg_imgs": {
					"left": "{\"attrs\":{\"x\":392,\"y\":199,\"width\":193.16666666666666,\"height\":61,\"strokeEnabled\":false,\"stroke\":\"Red\",\"strokeWidth\":3,\"name\":\"4\",\"draggable\":true,\"visible\":true},\"className\":\"Image\"}",
					"center": "{\"attrs\":{\"x\":367,\"y\":185,\"width\":180.5,\"height\":57,\"strokeEnabled\":false,\"stroke\":\"Red\",\"strokeWidth\":3,\"name\":\"4\",\"draggable\":true,\"visible\":true},\"className\":\"Image\"}",
					"right": "{\"attrs\":{\"x\":24,\"y\":313,\"width\":167.83333333333331,\"height\":53,\"strokeEnabled\":false,\"stroke\":\"Red\",\"strokeWidth\":3,\"name\":\"4\",\"draggable\":true,\"visible\":false},\"className\":\"Image\"}"
				},
				"alternate_id": 1,
				"region_id": -1,
				"curr_pos": {
					"x": 114.44442749023438,
					"y": 352
				},
				"img": "{\"attrs\":{\"x\":365,\"y\":186,\"width\":180.5,\"height\":57,\"strokeEnabled\":false,\"stroke\":\"Red\",\"strokeWidth\":3,\"name\":\"4\",\"draggable\":true,\"visible\":true,\"opacity\":1},\"className\":\"Image\"}",
				"sugg_img": "{\"attrs\":{\"x\":367,\"y\":185,\"width\":180.5,\"height\":57,\"strokeEnabled\":false,\"stroke\":\"Red\",\"strokeWidth\":3,\"name\":\"4\",\"draggable\":true,\"visible\":true},\"className\":\"Image\"}"
			},
			"3": {
				"id": 4,
				"text": "July 21 -\nAugust\n10, 2011",
				"type": "text",
				"importance": 1,
				"x": 24,
				"y": 313,
				"height": 53,
				"group_id": -1,
				"bold": false,
				"italic": false,
				"align": "left",
				"font": "Garamond",
				"color": "#FFFFFF",
				"loaded": true,
				"resizing": false,
				"fixed": false,
				"alternate": -1,
				"num_lines": 3,
				"num_alternates": -1,
				"selected": false,
				"old_text": "",
				"type_id": 1,
				"sugg_align": "left",
				"alternate_imgs": {
					"center": "{\"attrs\":{\"x\":35,\"y\":214,\"width\":301.32,\"height\":31,\"strokeEnabled\":false,\"stroke\":\"Red\",\"strokeWidth\":3,\"name\":\"4\",\"draggable\":true},\"className\":\"Image\"}"
				},
				"alternate_sugg_imgs": {
					"center": "{\"attrs\":{\"x\":35,\"y\":214,\"width\":301.32,\"height\":31,\"strokeEnabled\":false,\"stroke\":\"Red\",\"strokeWidth\":3,\"name\":\"4\",\"draggable\":true},\"className\":\"Image\"}"
				},
				"anchors": {
					"topLeft": "{\"attrs\":{\"x\":0,\"y\":0,\"fill\":\"#292\",\"opacity\":0.6,\"radius\":6,\"name\":\"topLeft\",\"draggable\":true,\"visible\":false},\"className\":\"Circle\"}",
					"topRight": "{\"attrs\":{\"x\":0,\"y\":0,\"fill\":\"#292\",\"opacity\":0.6,\"radius\":6,\"name\":\"topRight\",\"draggable\":true,\"visible\":false},\"className\":\"Circle\"}",
					"bottomLeft": "{\"attrs\":{\"x\":0,\"y\":0,\"fill\":\"#292\",\"opacity\":0.6,\"radius\":6,\"name\":\"bottomLeft\",\"draggable\":true,\"visible\":false},\"className\":\"Circle\"}",
					"bottomRight": "{\"attrs\":{\"x\":0,\"y\":0,\"fill\":\"#292\",\"opacity\":0.6,\"radius\":6,\"name\":\"bottomRight\",\"draggable\":true,\"visible\":false},\"className\":\"Circle\"}"
				},
				"aspect_ratio": 1.1,
				"fix_alignment": false,
				"width": 167.83333333333331,
				"fixed_amount": 0.25,
				"align_type": -1,
				"fix_alternate": false,
				"orig_text": "July 21 -\nAugust 10, 2011",
				"max_line_length": 9,
				"alignment_imgs": {
					"left": "{\"attrs\":{\"x\":24,\"y\":313,\"width\":58.300000000000004,\"height\":53,\"strokeEnabled\":false,\"stroke\":\"Red\",\"strokeWidth\":3,\"name\":\"4\",\"draggable\":true,\"visible\":false},\"className\":\"Image\"}",
					"center": "{\"attrs\":{\"x\":24,\"y\":313,\"width\":58.300000000000004,\"height\":53,\"strokeEnabled\":false,\"stroke\":\"Red\",\"strokeWidth\":3,\"name\":\"4\",\"draggable\":true,\"visible\":false},\"className\":\"Image\"}",
					"right": "{\"attrs\":{\"x\":24,\"y\":313,\"width\":58.300000000000004,\"height\":53,\"strokeEnabled\":false,\"stroke\":\"Red\",\"strokeWidth\":3,\"name\":\"4\",\"draggable\":true,\"visible\":false},\"className\":\"Image\"}"
				},
				"alignment_sugg_imgs": {
					"left": "{\"attrs\":{\"x\":24,\"y\":313,\"width\":58.300000000000004,\"height\":53,\"strokeEnabled\":false,\"stroke\":\"Red\",\"strokeWidth\":3,\"name\":\"4\",\"draggable\":true,\"visible\":false},\"className\":\"Image\"}",
					"center": "{\"attrs\":{\"x\":24,\"y\":313,\"width\":58.300000000000004,\"height\":53,\"strokeEnabled\":false,\"stroke\":\"Red\",\"strokeWidth\":3,\"name\":\"4\",\"draggable\":true,\"visible\":false},\"className\":\"Image\"}",
					"right": "{\"attrs\":{\"x\":24,\"y\":313,\"width\":58.300000000000004,\"height\":53,\"strokeEnabled\":false,\"stroke\":\"Red\",\"strokeWidth\":3,\"name\":\"4\",\"draggable\":true,\"visible\":false},\"className\":\"Image\"}"
				},
				"alternate_id": 2,
				"region_id": -1,
				"curr_pos": {
					"x": 114.44442749023438,
					"y": 352
				},
				"img": "{\"attrs\":{\"x\":24,\"y\":313,\"width\":58.300000000000004,\"height\":53,\"strokeEnabled\":false,\"stroke\":\"Red\",\"strokeWidth\":3,\"name\":\"4\",\"draggable\":true,\"visible\":false},\"className\":\"Image\"}",
				"sugg_img": "{\"attrs\":{\"x\":24,\"y\":313,\"width\":58.300000000000004,\"height\":53,\"strokeEnabled\":false,\"stroke\":\"Red\",\"strokeWidth\":3,\"name\":\"4\",\"draggable\":true,\"visible\":false},\"className\":\"Image\"}"
			},
			"4": {
				"id": 4,
				"text": "July 21\n-\nAugust 10,\n2011",
				"type": "text",
				"importance": 1,
				"x": 24,
				"y": 313,
				"height": 53,
				"group_id": -1,
				"bold": false,
				"italic": false,
				"align": "left",
				"font": "Garamond",
				"color": "#FFFFFF",
				"loaded": true,
				"resizing": false,
				"fixed": false,
				"alternate": -1,
				"num_lines": 4,
				"num_alternates": -1,
				"selected": false,
				"old_text": "",
				"type_id": 1,
				"sugg_align": "left",
				"alternate_imgs": {
					"center": "{\"attrs\":{\"x\":35,\"y\":214,\"width\":301.32,\"height\":31,\"strokeEnabled\":false,\"stroke\":\"Red\",\"strokeWidth\":3,\"name\":\"4\",\"draggable\":true},\"className\":\"Image\"}"
				},
				"alternate_sugg_imgs": {
					"center": "{\"attrs\":{\"x\":35,\"y\":214,\"width\":301.32,\"height\":31,\"strokeEnabled\":false,\"stroke\":\"Red\",\"strokeWidth\":3,\"name\":\"4\",\"draggable\":true},\"className\":\"Image\"}"
				},
				"anchors": {
					"topLeft": "{\"attrs\":{\"x\":0,\"y\":0,\"fill\":\"#292\",\"opacity\":0.6,\"radius\":6,\"name\":\"topLeft\",\"draggable\":true,\"visible\":false},\"className\":\"Circle\"}",
					"topRight": "{\"attrs\":{\"x\":0,\"y\":0,\"fill\":\"#292\",\"opacity\":0.6,\"radius\":6,\"name\":\"topRight\",\"draggable\":true,\"visible\":false},\"className\":\"Circle\"}",
					"bottomLeft": "{\"attrs\":{\"x\":0,\"y\":0,\"fill\":\"#292\",\"opacity\":0.6,\"radius\":6,\"name\":\"bottomLeft\",\"draggable\":true,\"visible\":false},\"className\":\"Circle\"}",
					"bottomRight": "{\"attrs\":{\"x\":0,\"y\":0,\"fill\":\"#292\",\"opacity\":0.6,\"radius\":6,\"name\":\"bottomRight\",\"draggable\":true,\"visible\":false},\"className\":\"Circle\"}"
				},
				"aspect_ratio": 1.0375,
				"fix_alignment": false,
				"width": 167.83333333333331,
				"fixed_amount": 0.25,
				"align_type": -1,
				"fix_alternate": false,
				"orig_text": "July 21 -\nAugust 10, 2011",
				"max_line_length": 10,
				"alignment_imgs": {
					"left": "{\"attrs\":{\"x\":24,\"y\":313,\"width\":54.987500000000004,\"height\":53,\"strokeEnabled\":false,\"stroke\":\"Red\",\"strokeWidth\":3,\"name\":\"4\",\"draggable\":true,\"visible\":false},\"className\":\"Image\"}",
					"center": "{\"attrs\":{\"x\":24,\"y\":313,\"width\":54.987500000000004,\"height\":53,\"strokeEnabled\":false,\"stroke\":\"Red\",\"strokeWidth\":3,\"name\":\"4\",\"draggable\":true,\"visible\":false},\"className\":\"Image\"}",
					"right": "{\"attrs\":{\"x\":24,\"y\":313,\"width\":54.987500000000004,\"height\":53,\"strokeEnabled\":false,\"stroke\":\"Red\",\"strokeWidth\":3,\"name\":\"4\",\"draggable\":true,\"visible\":false},\"className\":\"Image\"}"
				},
				"alignment_sugg_imgs": {
					"left": "{\"attrs\":{\"x\":24,\"y\":313,\"width\":54.987500000000004,\"height\":53,\"strokeEnabled\":false,\"stroke\":\"Red\",\"strokeWidth\":3,\"name\":\"4\",\"draggable\":true,\"visible\":false},\"className\":\"Image\"}",
					"center": "{\"attrs\":{\"x\":24,\"y\":313,\"width\":54.987500000000004,\"height\":53,\"strokeEnabled\":false,\"stroke\":\"Red\",\"strokeWidth\":3,\"name\":\"4\",\"draggable\":true,\"visible\":false},\"className\":\"Image\"}",
					"right": "{\"attrs\":{\"x\":24,\"y\":313,\"width\":54.987500000000004,\"height\":53,\"strokeEnabled\":false,\"stroke\":\"Red\",\"strokeWidth\":3,\"name\":\"4\",\"draggable\":true,\"visible\":false},\"className\":\"Image\"}"
				},
				"alternate_id": 3,
				"region_id": -1,
				"curr_pos": {
					"x": 114.44442749023438,
					"y": 352
				},
				"img": "{\"attrs\":{\"x\":24,\"y\":313,\"width\":54.987500000000004,\"height\":53,\"strokeEnabled\":false,\"stroke\":\"Red\",\"strokeWidth\":3,\"name\":\"4\",\"draggable\":true,\"visible\":false},\"className\":\"Image\"}",
				"sugg_img": "{\"attrs\":{\"x\":24,\"y\":313,\"width\":54.987500000000004,\"height\":53,\"strokeEnabled\":false,\"stroke\":\"Red\",\"strokeWidth\":3,\"name\":\"4\",\"draggable\":true,\"visible\":false},\"className\":\"Image\"}"
			},
			"5": {
				"id": 4,
				"text": "July\n21 -\nAugust\n10,\n2011",
				"type": "text",
				"importance": 1,
				"x": 24,
				"y": 313,
				"height": 53,
				"group_id": -1,
				"bold": false,
				"italic": false,
				"align": "left",
				"font": "Garamond",
				"color": "#FFFFFF",
				"loaded": true,
				"resizing": false,
				"fixed": false,
				"alternate": -1,
				"num_lines": 5,
				"num_alternates": -1,
				"selected": false,
				"old_text": "",
				"type_id": 1,
				"sugg_align": "left",
				"alternate_imgs": {
					"center": "{\"attrs\":{\"x\":35,\"y\":214,\"width\":301.32,\"height\":31,\"strokeEnabled\":false,\"stroke\":\"Red\",\"strokeWidth\":3,\"name\":\"4\",\"draggable\":true},\"className\":\"Image\"}"
				},
				"alternate_sugg_imgs": {
					"center": "{\"attrs\":{\"x\":35,\"y\":214,\"width\":301.32,\"height\":31,\"strokeEnabled\":false,\"stroke\":\"Red\",\"strokeWidth\":3,\"name\":\"4\",\"draggable\":true},\"className\":\"Image\"}"
				},
				"anchors": {
					"topLeft": "{\"attrs\":{\"x\":0,\"y\":0,\"fill\":\"#292\",\"opacity\":0.6,\"radius\":6,\"name\":\"topLeft\",\"draggable\":true,\"visible\":false},\"className\":\"Circle\"}",
					"topRight": "{\"attrs\":{\"x\":0,\"y\":0,\"fill\":\"#292\",\"opacity\":0.6,\"radius\":6,\"name\":\"topRight\",\"draggable\":true,\"visible\":false},\"className\":\"Circle\"}",
					"bottomLeft": "{\"attrs\":{\"x\":0,\"y\":0,\"fill\":\"#292\",\"opacity\":0.6,\"radius\":6,\"name\":\"bottomLeft\",\"draggable\":true,\"visible\":false},\"className\":\"Circle\"}",
					"bottomRight": "{\"attrs\":{\"x\":0,\"y\":0,\"fill\":\"#292\",\"opacity\":0.6,\"radius\":6,\"name\":\"bottomRight\",\"draggable\":true,\"visible\":false},\"className\":\"Circle\"}"
				},
				"aspect_ratio": 0.5555555555555556,
				"fix_alignment": false,
				"width": 167.83333333333331,
				"fixed_amount": 0.25,
				"align_type": -1,
				"fix_alternate": false,
				"orig_text": "July 21 -\nAugust 10, 2011",
				"max_line_length": 6,
				"alignment_imgs": {
					"left": "{\"attrs\":{\"x\":24,\"y\":313,\"width\":29.444444444444446,\"height\":53,\"strokeEnabled\":false,\"stroke\":\"Red\",\"strokeWidth\":3,\"name\":\"4\",\"draggable\":true,\"visible\":false},\"className\":\"Image\"}",
					"center": "{\"attrs\":{\"x\":24,\"y\":313,\"width\":29.444444444444446,\"height\":53,\"strokeEnabled\":false,\"stroke\":\"Red\",\"strokeWidth\":3,\"name\":\"4\",\"draggable\":true,\"visible\":false},\"className\":\"Image\"}",
					"right": "{\"attrs\":{\"x\":24,\"y\":313,\"width\":29.444444444444446,\"height\":53,\"strokeEnabled\":false,\"stroke\":\"Red\",\"strokeWidth\":3,\"name\":\"4\",\"draggable\":true,\"visible\":false},\"className\":\"Image\"}"
				},
				"alignment_sugg_imgs": {
					"left": "{\"attrs\":{\"x\":24,\"y\":313,\"width\":29.444444444444446,\"height\":53,\"strokeEnabled\":false,\"stroke\":\"Red\",\"strokeWidth\":3,\"name\":\"4\",\"draggable\":true,\"visible\":false},\"className\":\"Image\"}",
					"center": "{\"attrs\":{\"x\":24,\"y\":313,\"width\":29.444444444444446,\"height\":53,\"strokeEnabled\":false,\"stroke\":\"Red\",\"strokeWidth\":3,\"name\":\"4\",\"draggable\":true,\"visible\":false},\"className\":\"Image\"}",
					"right": "{\"attrs\":{\"x\":24,\"y\":313,\"width\":29.444444444444446,\"height\":53,\"strokeEnabled\":false,\"stroke\":\"Red\",\"strokeWidth\":3,\"name\":\"4\",\"draggable\":true,\"visible\":false},\"className\":\"Image\"}"
				},
				"alternate_id": 4,
				"region_id": -1,
				"curr_pos": {
					"x": 114.44442749023438,
					"y": 352
				},
				"img": "{\"attrs\":{\"x\":24,\"y\":313,\"width\":29.444444444444446,\"height\":53,\"strokeEnabled\":false,\"stroke\":\"Red\",\"strokeWidth\":3,\"name\":\"4\",\"draggable\":true,\"visible\":false},\"className\":\"Image\"}",
				"sugg_img": "{\"attrs\":{\"x\":24,\"y\":313,\"width\":29.444444444444446,\"height\":53,\"strokeEnabled\":false,\"stroke\":\"Red\",\"strokeWidth\":3,\"name\":\"4\",\"draggable\":true,\"visible\":false},\"className\":\"Image\"}"
			},
			"6": {
				"id": 4,
				"text": "July\n21 -\n\nAugust\n10,\n2011",
				"type": "text",
				"importance": 1,
				"x": 24,
				"y": 313,
				"height": 53,
				"group_id": -1,
				"bold": false,
				"italic": false,
				"align": "left",
				"font": "Garamond",
				"color": "#FFFFFF",
				"loaded": true,
				"resizing": false,
				"fixed": false,
				"alternate": -1,
				"num_lines": 6,
				"num_alternates": -1,
				"selected": false,
				"old_text": "",
				"type_id": 1,
				"sugg_align": "left",
				"alternate_imgs": {
					"center": "{\"attrs\":{\"x\":35,\"y\":214,\"width\":301.32,\"height\":31,\"strokeEnabled\":false,\"stroke\":\"Red\",\"strokeWidth\":3,\"name\":\"4\",\"draggable\":true},\"className\":\"Image\"}"
				},
				"alternate_sugg_imgs": {
					"center": "{\"attrs\":{\"x\":35,\"y\":214,\"width\":301.32,\"height\":31,\"strokeEnabled\":false,\"stroke\":\"Red\",\"strokeWidth\":3,\"name\":\"4\",\"draggable\":true},\"className\":\"Image\"}"
				},
				"anchors": {
					"topLeft": "{\"attrs\":{\"x\":0,\"y\":0,\"fill\":\"#292\",\"opacity\":0.6,\"radius\":6,\"name\":\"topLeft\",\"draggable\":true,\"visible\":false},\"className\":\"Circle\"}",
					"topRight": "{\"attrs\":{\"x\":0,\"y\":0,\"fill\":\"#292\",\"opacity\":0.6,\"radius\":6,\"name\":\"topRight\",\"draggable\":true,\"visible\":false},\"className\":\"Circle\"}",
					"bottomLeft": "{\"attrs\":{\"x\":0,\"y\":0,\"fill\":\"#292\",\"opacity\":0.6,\"radius\":6,\"name\":\"bottomLeft\",\"draggable\":true,\"visible\":false},\"className\":\"Circle\"}",
					"bottomRight": "{\"attrs\":{\"x\":0,\"y\":0,\"fill\":\"#292\",\"opacity\":0.6,\"radius\":6,\"name\":\"bottomRight\",\"draggable\":true,\"visible\":false},\"className\":\"Circle\"}"
				},
				"aspect_ratio": 0.47,
				"fix_alignment": false,
				"width": 167.83333333333331,
				"fixed_amount": 0.25,
				"align_type": -1,
				"fix_alternate": false,
				"orig_text": "July 21 -\nAugust 10, 2011",
				"max_line_length": 6,
				"alignment_imgs": {
					"left": "{\"attrs\":{\"x\":24,\"y\":313,\"width\":24.91,\"height\":53,\"strokeEnabled\":false,\"stroke\":\"Red\",\"strokeWidth\":3,\"name\":\"4\",\"draggable\":true,\"visible\":false},\"className\":\"Image\"}",
					"center": "{\"attrs\":{\"x\":24,\"y\":313,\"width\":24.91,\"height\":53,\"strokeEnabled\":false,\"stroke\":\"Red\",\"strokeWidth\":3,\"name\":\"4\",\"draggable\":true,\"visible\":false},\"className\":\"Image\"}",
					"right": "{\"attrs\":{\"x\":24,\"y\":313,\"width\":24.91,\"height\":53,\"strokeEnabled\":false,\"stroke\":\"Red\",\"strokeWidth\":3,\"name\":\"4\",\"draggable\":true,\"visible\":false},\"className\":\"Image\"}"
				},
				"alignment_sugg_imgs": {
					"left": "{\"attrs\":{\"x\":24,\"y\":313,\"width\":24.91,\"height\":53,\"strokeEnabled\":false,\"stroke\":\"Red\",\"strokeWidth\":3,\"name\":\"4\",\"draggable\":true,\"visible\":false},\"className\":\"Image\"}",
					"center": "{\"attrs\":{\"x\":24,\"y\":313,\"width\":24.91,\"height\":53,\"strokeEnabled\":false,\"stroke\":\"Red\",\"strokeWidth\":3,\"name\":\"4\",\"draggable\":true,\"visible\":false},\"className\":\"Image\"}",
					"right": "{\"attrs\":{\"x\":24,\"y\":313,\"width\":24.91,\"height\":53,\"strokeEnabled\":false,\"stroke\":\"Red\",\"strokeWidth\":3,\"name\":\"4\",\"draggable\":true,\"visible\":false},\"className\":\"Image\"}"
				},
				"alternate_id": 5,
				"region_id": -1,
				"curr_pos": {
					"x": 114.44442749023438,
					"y": 352
				},
				"img": "{\"attrs\":{\"x\":24,\"y\":313,\"width\":24.91,\"height\":53,\"strokeEnabled\":false,\"stroke\":\"Red\",\"strokeWidth\":3,\"name\":\"4\",\"draggable\":true,\"visible\":false},\"className\":\"Image\"}",
				"sugg_img": "{\"attrs\":{\"x\":24,\"y\":313,\"width\":24.91,\"height\":53,\"strokeEnabled\":false,\"stroke\":\"Red\",\"strokeWidth\":3,\"name\":\"4\",\"draggable\":true,\"visible\":false},\"className\":\"Image\"}"
			}
		},
		"5": {
			"1": {
				"id": 5,
				"text": "Gallery 81 812 Spadina Ave Toronto",
				"type": "text",
				"importance": 0,
				"x": 209,
				"y": 301,
				"height": 70,
				"bold": false,
				"italic": false,
				"group_id": -1,
				"align": "left",
				"font": "Garamond",
				"color": "#FFFFFF",
				"loaded": true,
				"resizing": false,
				"fixed": false,
				"alternate": -1,
				"num_lines": 1,
				"num_alternates": 3,
				"selected": false,
				"old_text": "",
				"type_id": 1,
				"sugg_align": "left",
				"alternate_imgs": {
					"left": "{\"attrs\":{\"x\":92,\"y\":271,\"width\":186.74285714285713,\"height\":86,\"strokeEnabled\":false,\"stroke\":\"Red\",\"strokeWidth\":3,\"name\":\"5\",\"draggable\":true},\"className\":\"Image\"}",
					"center": "{\"attrs\":{\"x\":96,\"y\":273,\"width\":180.22857142857143,\"height\":83,\"strokeEnabled\":false,\"stroke\":\"Red\",\"strokeWidth\":3,\"name\":\"5\",\"draggable\":true},\"className\":\"Image\"}",
					"right": "{\"attrs\":{\"x\":92,\"y\":271,\"width\":186.74285714285713,\"height\":86,\"strokeEnabled\":false,\"stroke\":\"Red\",\"strokeWidth\":3,\"name\":\"5\",\"draggable\":true},\"className\":\"Image\"}"
				},
				"alternate_sugg_imgs": {
					"left": "{\"attrs\":{\"x\":92,\"y\":271,\"width\":186.74285714285713,\"height\":86,\"strokeEnabled\":false,\"stroke\":\"Red\",\"strokeWidth\":3,\"name\":\"5\",\"draggable\":true},\"className\":\"Image\"}",
					"center": "{\"attrs\":{\"x\":96,\"y\":273,\"width\":180.22857142857143,\"height\":83,\"strokeEnabled\":false,\"stroke\":\"Red\",\"strokeWidth\":3,\"name\":\"5\",\"draggable\":true},\"className\":\"Image\"}",
					"right": "{\"attrs\":{\"x\":92,\"y\":271,\"width\":186.74285714285713,\"height\":86,\"strokeEnabled\":false,\"stroke\":\"Red\",\"strokeWidth\":3,\"name\":\"5\",\"draggable\":true},\"className\":\"Image\"}"
				},
				"anchors": {
					"topLeft": "{\"attrs\":{\"x\":0,\"y\":0,\"fill\":\"#292\",\"opacity\":0.6,\"radius\":6,\"name\":\"topLeft\",\"draggable\":true,\"visible\":false},\"className\":\"Circle\"}",
					"topRight": "{\"attrs\":{\"x\":0,\"y\":0,\"fill\":\"#292\",\"opacity\":0.6,\"radius\":6,\"name\":\"topRight\",\"draggable\":true,\"visible\":false},\"className\":\"Circle\"}",
					"bottomLeft": "{\"attrs\":{\"x\":0,\"y\":0,\"fill\":\"#292\",\"opacity\":0.6,\"radius\":6,\"name\":\"bottomLeft\",\"draggable\":true,\"visible\":false},\"className\":\"Circle\"}",
					"bottomRight": "{\"attrs\":{\"x\":0,\"y\":0,\"fill\":\"#292\",\"opacity\":0.6,\"radius\":6,\"name\":\"bottomRight\",\"draggable\":true,\"visible\":false},\"className\":\"Circle\"}"
				},
				"aspect_ratio": 14.34,
				"fix_alignment": false,
				"width": 152,
				"fixed_amount": 0.25,
				"align_type": -1,
				"fix_alternate": false,
				"orig_text": "Gallery 81\n812 Spadina Ave\nToronto",
				"max_line_length": 34,
				"alignment_imgs": {
					"left": "{\"attrs\":{\"x\":209,\"y\":301,\"width\":1003.8,\"height\":70,\"strokeEnabled\":false,\"stroke\":\"Red\",\"strokeWidth\":3,\"name\":\"5\",\"draggable\":true,\"visible\":false},\"className\":\"Image\"}"
				},
				"alignment_sugg_imgs": {
					"left": "{\"attrs\":{\"x\":209,\"y\":301,\"width\":1003.8,\"height\":70,\"strokeEnabled\":false,\"stroke\":\"Red\",\"strokeWidth\":3,\"name\":\"5\",\"draggable\":true,\"visible\":false},\"className\":\"Image\"}"
				},
				"alternate_id": 0,
				"region_id": -1,
				"curr_pos": {
					"x": 354.4444274902344,
					"y": 340
				},
				"img": "{\"attrs\":{\"x\":209,\"y\":301,\"width\":1003.8,\"height\":70,\"strokeEnabled\":false,\"stroke\":\"Red\",\"strokeWidth\":3,\"name\":\"5\",\"draggable\":true,\"visible\":false},\"className\":\"Image\"}",
				"sugg_img": "{\"attrs\":{\"x\":209,\"y\":301,\"width\":1003.8,\"height\":70,\"strokeEnabled\":false,\"stroke\":\"Red\",\"strokeWidth\":3,\"name\":\"5\",\"draggable\":true,\"visible\":false},\"className\":\"Image\"}"
			},
			"2": {
				"id": 5,
				"text": "Gallery 81 812\nSpadina Ave Toronto",
				"type": "text",
				"importance": 0,
				"x": 209,
				"y": 301,
				"height": 70,
				"bold": false,
				"italic": false,
				"group_id": -1,
				"align": "left",
				"font": "Garamond",
				"color": "#FFFFFF",
				"loaded": true,
				"resizing": false,
				"fixed": false,
				"alternate": -1,
				"num_lines": 2,
				"num_alternates": 3,
				"selected": false,
				"old_text": "",
				"type_id": 1,
				"sugg_align": "left",
				"alternate_imgs": {
					"left": "{\"attrs\":{\"x\":92,\"y\":271,\"width\":186.74285714285713,\"height\":86,\"strokeEnabled\":false,\"stroke\":\"Red\",\"strokeWidth\":3,\"name\":\"5\",\"draggable\":true},\"className\":\"Image\"}",
					"center": "{\"attrs\":{\"x\":96,\"y\":273,\"width\":180.22857142857143,\"height\":83,\"strokeEnabled\":false,\"stroke\":\"Red\",\"strokeWidth\":3,\"name\":\"5\",\"draggable\":true},\"className\":\"Image\"}",
					"right": "{\"attrs\":{\"x\":92,\"y\":271,\"width\":186.74285714285713,\"height\":86,\"strokeEnabled\":false,\"stroke\":\"Red\",\"strokeWidth\":3,\"name\":\"5\",\"draggable\":true},\"className\":\"Image\"}"
				},
				"alternate_sugg_imgs": {
					"left": "{\"attrs\":{\"x\":92,\"y\":271,\"width\":186.74285714285713,\"height\":86,\"strokeEnabled\":false,\"stroke\":\"Red\",\"strokeWidth\":3,\"name\":\"5\",\"draggable\":true},\"className\":\"Image\"}",
					"center": "{\"attrs\":{\"x\":96,\"y\":273,\"width\":180.22857142857143,\"height\":83,\"strokeEnabled\":false,\"stroke\":\"Red\",\"strokeWidth\":3,\"name\":\"5\",\"draggable\":true},\"className\":\"Image\"}",
					"right": "{\"attrs\":{\"x\":92,\"y\":271,\"width\":186.74285714285713,\"height\":86,\"strokeEnabled\":false,\"stroke\":\"Red\",\"strokeWidth\":3,\"name\":\"5\",\"draggable\":true},\"className\":\"Image\"}"
				},
				"anchors": {
					"topLeft": "{\"attrs\":{\"x\":0,\"y\":0,\"fill\":\"#292\",\"opacity\":0.6,\"radius\":6,\"name\":\"topLeft\",\"draggable\":true,\"visible\":false},\"className\":\"Circle\"}",
					"topRight": "{\"attrs\":{\"x\":0,\"y\":0,\"fill\":\"#292\",\"opacity\":0.6,\"radius\":6,\"name\":\"topRight\",\"draggable\":true,\"visible\":false},\"className\":\"Circle\"}",
					"bottomLeft": "{\"attrs\":{\"x\":0,\"y\":0,\"fill\":\"#292\",\"opacity\":0.6,\"radius\":6,\"name\":\"bottomLeft\",\"draggable\":true,\"visible\":false},\"className\":\"Circle\"}",
					"bottomRight": "{\"attrs\":{\"x\":0,\"y\":0,\"fill\":\"#292\",\"opacity\":0.6,\"radius\":6,\"name\":\"bottomRight\",\"draggable\":true,\"visible\":false},\"className\":\"Circle\"}"
				},
				"aspect_ratio": 4.15,
				"fix_alignment": false,
				"width": 152,
				"fixed_amount": 0.25,
				"align_type": -1,
				"fix_alternate": false,
				"orig_text": "Gallery 81\n812 Spadina Ave\nToronto",
				"max_line_length": 19,
				"alignment_imgs": {
					"left": "{\"attrs\":{\"x\":209,\"y\":301,\"width\":290.5,\"height\":70,\"strokeEnabled\":false,\"stroke\":\"Red\",\"strokeWidth\":3,\"name\":\"5\",\"draggable\":true,\"visible\":false},\"className\":\"Image\"}",
					"center": "{\"attrs\":{\"x\":209,\"y\":301,\"width\":290.5,\"height\":70,\"strokeEnabled\":false,\"stroke\":\"Red\",\"strokeWidth\":3,\"name\":\"5\",\"draggable\":true,\"visible\":false},\"className\":\"Image\"}",
					"right": "{\"attrs\":{\"x\":209,\"y\":301,\"width\":290.5,\"height\":70,\"strokeEnabled\":false,\"stroke\":\"Red\",\"strokeWidth\":3,\"name\":\"5\",\"draggable\":true,\"visible\":false},\"className\":\"Image\"}"
				},
				"alignment_sugg_imgs": {
					"left": "{\"attrs\":{\"x\":209,\"y\":301,\"width\":290.5,\"height\":70,\"strokeEnabled\":false,\"stroke\":\"Red\",\"strokeWidth\":3,\"name\":\"5\",\"draggable\":true,\"visible\":false},\"className\":\"Image\"}",
					"center": "{\"attrs\":{\"x\":209,\"y\":301,\"width\":290.5,\"height\":70,\"strokeEnabled\":false,\"stroke\":\"Red\",\"strokeWidth\":3,\"name\":\"5\",\"draggable\":true,\"visible\":false},\"className\":\"Image\"}",
					"right": "{\"attrs\":{\"x\":209,\"y\":301,\"width\":290.5,\"height\":70,\"strokeEnabled\":false,\"stroke\":\"Red\",\"strokeWidth\":3,\"name\":\"5\",\"draggable\":true,\"visible\":false},\"className\":\"Image\"}"
				},
				"alternate_id": 1,
				"region_id": -1,
				"curr_pos": {
					"x": 354.4444274902344,
					"y": 340
				},
				"img": "{\"attrs\":{\"x\":209,\"y\":301,\"width\":290.5,\"height\":70,\"strokeEnabled\":false,\"stroke\":\"Red\",\"strokeWidth\":3,\"name\":\"5\",\"draggable\":true,\"visible\":false},\"className\":\"Image\"}",
				"sugg_img": "{\"attrs\":{\"x\":209,\"y\":301,\"width\":290.5,\"height\":70,\"strokeEnabled\":false,\"stroke\":\"Red\",\"strokeWidth\":3,\"name\":\"5\",\"draggable\":true,\"visible\":false},\"className\":\"Image\"}"
			},
			"3": {
				"id": 5,
				"text": "Gallery 81\n812 Spadina Ave\nToronto",
				"type": "text",
				"importance": 0,
				"x": 394,
				"y": 311,
				"height": 56,
				"bold": false,
				"italic": false,
				"group_id": -1,
				"align": "center",
				"font": "Garamond",
				"color": "#FFFFFF",
				"loaded": true,
				"resizing": false,
				"fixed": false,
				"alternate": -1,
				"num_lines": 3,
				"num_alternates": 3,
				"selected": false,
				"old_text": "",
				"type_id": 1,
				"sugg_align": "center",
				"alternate_imgs": {
					"left": "{\"attrs\":{\"x\":92,\"y\":271,\"width\":186.74285714285713,\"height\":86,\"strokeEnabled\":false,\"stroke\":\"Red\",\"strokeWidth\":3,\"name\":\"5\",\"draggable\":true},\"className\":\"Image\"}",
					"center": "{\"attrs\":{\"x\":96,\"y\":273,\"width\":180.22857142857143,\"height\":83,\"strokeEnabled\":false,\"stroke\":\"Red\",\"strokeWidth\":3,\"name\":\"5\",\"draggable\":true},\"className\":\"Image\"}",
					"right": "{\"attrs\":{\"x\":92,\"y\":271,\"width\":186.74285714285713,\"height\":86,\"strokeEnabled\":false,\"stroke\":\"Red\",\"strokeWidth\":3,\"name\":\"5\",\"draggable\":true},\"className\":\"Image\"}"
				},
				"alternate_sugg_imgs": {
					"left": "{\"attrs\":{\"x\":92,\"y\":271,\"width\":186.74285714285713,\"height\":86,\"strokeEnabled\":false,\"stroke\":\"Red\",\"strokeWidth\":3,\"name\":\"5\",\"draggable\":true},\"className\":\"Image\"}",
					"center": "{\"attrs\":{\"x\":96,\"y\":273,\"width\":180.22857142857143,\"height\":83,\"strokeEnabled\":false,\"stroke\":\"Red\",\"strokeWidth\":3,\"name\":\"5\",\"draggable\":true},\"className\":\"Image\"}",
					"right": "{\"attrs\":{\"x\":92,\"y\":271,\"width\":186.74285714285713,\"height\":86,\"strokeEnabled\":false,\"stroke\":\"Red\",\"strokeWidth\":3,\"name\":\"5\",\"draggable\":true},\"className\":\"Image\"}"
				},
				"anchors": {
					"topLeft": "{\"attrs\":{\"x\":394,\"y\":367,\"fill\":\"#292\",\"opacity\":0.6,\"radius\":6,\"name\":\"topLeft\",\"draggable\":true,\"visible\":false},\"className\":\"Circle\"}",
					"topRight": "{\"attrs\":{\"x\":515.6,\"y\":367,\"fill\":\"#292\",\"opacity\":0.6,\"radius\":6,\"name\":\"topRight\",\"draggable\":true,\"visible\":false},\"className\":\"Circle\"}",
					"bottomLeft": "{\"attrs\":{\"x\":394,\"y\":311,\"fill\":\"#292\",\"opacity\":0.6,\"radius\":6,\"name\":\"bottomLeft\",\"draggable\":true,\"visible\":false},\"className\":\"Circle\"}",
					"bottomRight": "{\"attrs\":{\"x\":515.6,\"y\":311,\"fill\":\"#292\",\"opacity\":0.6,\"radius\":6,\"name\":\"bottomRight\",\"draggable\":true,\"visible\":false},\"className\":\"Circle\"}"
				},
				"aspect_ratio": 2.1714285714285713,
				"fix_alignment": false,
				"width": 121.6,
				"fixed_amount": 0.6961227826125412,
				"align_type": 1,
				"fix_alternate": false,
				"orig_text": "Gallery 81\n812 Spadina Ave\nToronto",
				"max_line_length": 15,
				"alignment_imgs": {
					"left": "{\"attrs\":{\"x\":392,\"y\":304,\"width\":134.6285714285714,\"height\":62,\"strokeEnabled\":false,\"stroke\":\"Red\",\"strokeWidth\":3,\"name\":\"5\",\"draggable\":true,\"visible\":true,\"opacity\":1},\"className\":\"Image\"}",
					"center": "{\"attrs\":{\"x\":394,\"y\":311,\"width\":121.6,\"height\":56,\"strokeEnabled\":false,\"stroke\":\"Red\",\"strokeWidth\":3,\"name\":\"5\",\"draggable\":true,\"visible\":true,\"opacity\":1,\"rotation\":0,\"scaleX\":1,\"scaleY\":1,\"offsetX\":0,\"offsetY\":0,\"skewX\":0,\"skewY\":0},\"className\":\"Image\"}",
					"right": "{\"attrs\":{\"x\":209,\"y\":301,\"width\":152,\"height\":70,\"strokeEnabled\":false,\"stroke\":\"Red\",\"strokeWidth\":3,\"name\":\"5\",\"draggable\":true,\"visible\":false},\"className\":\"Image\"}"
				},
				"alignment_sugg_imgs": {
					"left": "{\"attrs\":{\"x\":392,\"y\":304,\"width\":134.6285714285714,\"height\":62,\"strokeEnabled\":false,\"stroke\":\"Red\",\"strokeWidth\":3,\"name\":\"5\",\"draggable\":true,\"visible\":true},\"className\":\"Image\"}",
					"center": "{\"attrs\":{\"x\":394,\"y\":309,\"width\":123.77142857142856,\"height\":57,\"strokeEnabled\":false,\"stroke\":\"Red\",\"strokeWidth\":3,\"name\":\"5\",\"draggable\":true,\"visible\":true},\"className\":\"Image\"}",
					"right": "{\"attrs\":{\"x\":209,\"y\":301,\"width\":152,\"height\":70,\"strokeEnabled\":false,\"stroke\":\"Red\",\"strokeWidth\":3,\"name\":\"5\",\"draggable\":true,\"visible\":false},\"className\":\"Image\"}"
				},
				"alternate_id": 2,
				"region_id": -1,
				"curr_pos": {
					"x": 449.111083984375,
					"y": 338
				},
				"img": "{\"attrs\":{\"x\":394,\"y\":311,\"width\":121.6,\"height\":56,\"strokeEnabled\":false,\"stroke\":\"Red\",\"strokeWidth\":3,\"name\":\"5\",\"draggable\":true,\"visible\":true,\"opacity\":1,\"rotation\":0,\"scaleX\":1,\"scaleY\":1,\"offsetX\":0,\"offsetY\":0,\"skewX\":0,\"skewY\":0},\"className\":\"Image\"}",
				"sugg_img": "{\"attrs\":{\"x\":394,\"y\":309,\"width\":123.77142857142856,\"height\":57,\"strokeEnabled\":false,\"stroke\":\"Red\",\"strokeWidth\":3,\"name\":\"5\",\"draggable\":true,\"visible\":true},\"className\":\"Image\"}"
			},
			"4": {
				"id": 5,
				"text": "Gallery\n81 812\nSpadina\nAve Toronto",
				"type": "text",
				"importance": 0,
				"x": 209,
				"y": 301,
				"height": 70,
				"bold": false,
				"italic": false,
				"group_id": -1,
				"align": "left",
				"font": "Garamond",
				"color": "#FFFFFF",
				"loaded": true,
				"resizing": false,
				"fixed": false,
				"alternate": -1,
				"num_lines": 4,
				"num_alternates": 3,
				"selected": false,
				"old_text": "",
				"type_id": 1,
				"sugg_align": "left",
				"alternate_imgs": {
					"left": "{\"attrs\":{\"x\":92,\"y\":271,\"width\":186.74285714285713,\"height\":86,\"strokeEnabled\":false,\"stroke\":\"Red\",\"strokeWidth\":3,\"name\":\"5\",\"draggable\":true},\"className\":\"Image\"}",
					"center": "{\"attrs\":{\"x\":96,\"y\":273,\"width\":180.22857142857143,\"height\":83,\"strokeEnabled\":false,\"stroke\":\"Red\",\"strokeWidth\":3,\"name\":\"5\",\"draggable\":true},\"className\":\"Image\"}",
					"right": "{\"attrs\":{\"x\":92,\"y\":271,\"width\":186.74285714285713,\"height\":86,\"strokeEnabled\":false,\"stroke\":\"Red\",\"strokeWidth\":3,\"name\":\"5\",\"draggable\":true},\"className\":\"Image\"}"
				},
				"alternate_sugg_imgs": {
					"left": "{\"attrs\":{\"x\":92,\"y\":271,\"width\":186.74285714285713,\"height\":86,\"strokeEnabled\":false,\"stroke\":\"Red\",\"strokeWidth\":3,\"name\":\"5\",\"draggable\":true},\"className\":\"Image\"}",
					"center": "{\"attrs\":{\"x\":96,\"y\":273,\"width\":180.22857142857143,\"height\":83,\"strokeEnabled\":false,\"stroke\":\"Red\",\"strokeWidth\":3,\"name\":\"5\",\"draggable\":true},\"className\":\"Image\"}",
					"right": "{\"attrs\":{\"x\":92,\"y\":271,\"width\":186.74285714285713,\"height\":86,\"strokeEnabled\":false,\"stroke\":\"Red\",\"strokeWidth\":3,\"name\":\"5\",\"draggable\":true},\"className\":\"Image\"}"
				},
				"anchors": {
					"topLeft": "{\"attrs\":{\"x\":0,\"y\":0,\"fill\":\"#292\",\"opacity\":0.6,\"radius\":6,\"name\":\"topLeft\",\"draggable\":true,\"visible\":false},\"className\":\"Circle\"}",
					"topRight": "{\"attrs\":{\"x\":0,\"y\":0,\"fill\":\"#292\",\"opacity\":0.6,\"radius\":6,\"name\":\"topRight\",\"draggable\":true,\"visible\":false},\"className\":\"Circle\"}",
					"bottomLeft": "{\"attrs\":{\"x\":0,\"y\":0,\"fill\":\"#292\",\"opacity\":0.6,\"radius\":6,\"name\":\"bottomLeft\",\"draggable\":true,\"visible\":false},\"className\":\"Circle\"}",
					"bottomRight": "{\"attrs\":{\"x\":0,\"y\":0,\"fill\":\"#292\",\"opacity\":0.6,\"radius\":6,\"name\":\"bottomRight\",\"draggable\":true,\"visible\":false},\"className\":\"Circle\"}"
				},
				"aspect_ratio": 1.2625,
				"fix_alignment": false,
				"width": 152,
				"fixed_amount": 0.25,
				"align_type": -1,
				"fix_alternate": false,
				"orig_text": "Gallery 81\n812 Spadina Ave\nToronto",
				"max_line_length": 11,
				"alignment_imgs": {
					"left": "{\"attrs\":{\"x\":209,\"y\":301,\"width\":88.375,\"height\":70,\"strokeEnabled\":false,\"stroke\":\"Red\",\"strokeWidth\":3,\"name\":\"5\",\"draggable\":true,\"visible\":false},\"className\":\"Image\"}",
					"center": "{\"attrs\":{\"x\":209,\"y\":301,\"width\":88.375,\"height\":70,\"strokeEnabled\":false,\"stroke\":\"Red\",\"strokeWidth\":3,\"name\":\"5\",\"draggable\":true,\"visible\":false},\"className\":\"Image\"}",
					"right": "{\"attrs\":{\"x\":209,\"y\":301,\"width\":88.375,\"height\":70,\"strokeEnabled\":false,\"stroke\":\"Red\",\"strokeWidth\":3,\"name\":\"5\",\"draggable\":true,\"visible\":false},\"className\":\"Image\"}"
				},
				"alignment_sugg_imgs": {
					"left": "{\"attrs\":{\"x\":209,\"y\":301,\"width\":88.375,\"height\":70,\"strokeEnabled\":false,\"stroke\":\"Red\",\"strokeWidth\":3,\"name\":\"5\",\"draggable\":true,\"visible\":false},\"className\":\"Image\"}",
					"center": "{\"attrs\":{\"x\":209,\"y\":301,\"width\":88.375,\"height\":70,\"strokeEnabled\":false,\"stroke\":\"Red\",\"strokeWidth\":3,\"name\":\"5\",\"draggable\":true,\"visible\":false},\"className\":\"Image\"}",
					"right": "{\"attrs\":{\"x\":209,\"y\":301,\"width\":88.375,\"height\":70,\"strokeEnabled\":false,\"stroke\":\"Red\",\"strokeWidth\":3,\"name\":\"5\",\"draggable\":true,\"visible\":false},\"className\":\"Image\"}"
				},
				"alternate_id": 3,
				"region_id": -1,
				"curr_pos": {
					"x": 354.4444274902344,
					"y": 340
				},
				"img": "{\"attrs\":{\"x\":209,\"y\":301,\"width\":88.375,\"height\":70,\"strokeEnabled\":false,\"stroke\":\"Red\",\"strokeWidth\":3,\"name\":\"5\",\"draggable\":true,\"visible\":false},\"className\":\"Image\"}",
				"sugg_img": "{\"attrs\":{\"x\":209,\"y\":301,\"width\":88.375,\"height\":70,\"strokeEnabled\":false,\"stroke\":\"Red\",\"strokeWidth\":3,\"name\":\"5\",\"draggable\":true,\"visible\":false},\"className\":\"Image\"}"
			},
			"5": {
				"id": 5,
				"text": "Gallery\n81\n812\nSpadina\nAve Toronto",
				"type": "text",
				"importance": 0,
				"x": 209,
				"y": 301,
				"height": 70,
				"bold": false,
				"italic": false,
				"group_id": -1,
				"align": "left",
				"font": "Garamond",
				"color": "#FFFFFF",
				"loaded": true,
				"resizing": false,
				"fixed": false,
				"alternate": -1,
				"num_lines": 5,
				"num_alternates": 3,
				"selected": false,
				"old_text": "",
				"type_id": 1,
				"sugg_align": "left",
				"alternate_imgs": {
					"left": "{\"attrs\":{\"x\":92,\"y\":271,\"width\":186.74285714285713,\"height\":86,\"strokeEnabled\":false,\"stroke\":\"Red\",\"strokeWidth\":3,\"name\":\"5\",\"draggable\":true},\"className\":\"Image\"}",
					"center": "{\"attrs\":{\"x\":96,\"y\":273,\"width\":180.22857142857143,\"height\":83,\"strokeEnabled\":false,\"stroke\":\"Red\",\"strokeWidth\":3,\"name\":\"5\",\"draggable\":true},\"className\":\"Image\"}",
					"right": "{\"attrs\":{\"x\":92,\"y\":271,\"width\":186.74285714285713,\"height\":86,\"strokeEnabled\":false,\"stroke\":\"Red\",\"strokeWidth\":3,\"name\":\"5\",\"draggable\":true},\"className\":\"Image\"}"
				},
				"alternate_sugg_imgs": {
					"left": "{\"attrs\":{\"x\":92,\"y\":271,\"width\":186.74285714285713,\"height\":86,\"strokeEnabled\":false,\"stroke\":\"Red\",\"strokeWidth\":3,\"name\":\"5\",\"draggable\":true},\"className\":\"Image\"}",
					"center": "{\"attrs\":{\"x\":96,\"y\":273,\"width\":180.22857142857143,\"height\":83,\"strokeEnabled\":false,\"stroke\":\"Red\",\"strokeWidth\":3,\"name\":\"5\",\"draggable\":true},\"className\":\"Image\"}",
					"right": "{\"attrs\":{\"x\":92,\"y\":271,\"width\":186.74285714285713,\"height\":86,\"strokeEnabled\":false,\"stroke\":\"Red\",\"strokeWidth\":3,\"name\":\"5\",\"draggable\":true},\"className\":\"Image\"}"
				},
				"anchors": {
					"topLeft": "{\"attrs\":{\"x\":0,\"y\":0,\"fill\":\"#292\",\"opacity\":0.6,\"radius\":6,\"name\":\"topLeft\",\"draggable\":true,\"visible\":false},\"className\":\"Circle\"}",
					"topRight": "{\"attrs\":{\"x\":0,\"y\":0,\"fill\":\"#292\",\"opacity\":0.6,\"radius\":6,\"name\":\"topRight\",\"draggable\":true,\"visible\":false},\"className\":\"Circle\"}",
					"bottomLeft": "{\"attrs\":{\"x\":0,\"y\":0,\"fill\":\"#292\",\"opacity\":0.6,\"radius\":6,\"name\":\"bottomLeft\",\"draggable\":true,\"visible\":false},\"className\":\"Circle\"}",
					"bottomRight": "{\"attrs\":{\"x\":0,\"y\":0,\"fill\":\"#292\",\"opacity\":0.6,\"radius\":6,\"name\":\"bottomRight\",\"draggable\":true,\"visible\":false},\"className\":\"Circle\"}"
				},
				"aspect_ratio": 1,
				"fix_alignment": false,
				"width": 152,
				"fixed_amount": 0.25,
				"align_type": -1,
				"fix_alternate": false,
				"orig_text": "Gallery 81\n812 Spadina Ave\nToronto",
				"max_line_length": 11,
				"alignment_imgs": {
					"left": "{\"attrs\":{\"x\":209,\"y\":301,\"width\":70,\"height\":70,\"strokeEnabled\":false,\"stroke\":\"Red\",\"strokeWidth\":3,\"name\":\"5\",\"draggable\":true,\"visible\":false},\"className\":\"Image\"}",
					"center": "{\"attrs\":{\"x\":209,\"y\":301,\"width\":70,\"height\":70,\"strokeEnabled\":false,\"stroke\":\"Red\",\"strokeWidth\":3,\"name\":\"5\",\"draggable\":true,\"visible\":false},\"className\":\"Image\"}",
					"right": "{\"attrs\":{\"x\":209,\"y\":301,\"width\":70,\"height\":70,\"strokeEnabled\":false,\"stroke\":\"Red\",\"strokeWidth\":3,\"name\":\"5\",\"draggable\":true,\"visible\":false},\"className\":\"Image\"}"
				},
				"alignment_sugg_imgs": {
					"left": "{\"attrs\":{\"x\":209,\"y\":301,\"width\":70,\"height\":70,\"strokeEnabled\":false,\"stroke\":\"Red\",\"strokeWidth\":3,\"name\":\"5\",\"draggable\":true,\"visible\":false},\"className\":\"Image\"}",
					"center": "{\"attrs\":{\"x\":209,\"y\":301,\"width\":70,\"height\":70,\"strokeEnabled\":false,\"stroke\":\"Red\",\"strokeWidth\":3,\"name\":\"5\",\"draggable\":true,\"visible\":false},\"className\":\"Image\"}",
					"right": "{\"attrs\":{\"x\":209,\"y\":301,\"width\":70,\"height\":70,\"strokeEnabled\":false,\"stroke\":\"Red\",\"strokeWidth\":3,\"name\":\"5\",\"draggable\":true,\"visible\":false},\"className\":\"Image\"}"
				},
				"alternate_id": 4,
				"region_id": -1,
				"curr_pos": {
					"x": 354.4444274902344,
					"y": 340
				},
				"img": "{\"attrs\":{\"x\":209,\"y\":301,\"width\":70,\"height\":70,\"strokeEnabled\":false,\"stroke\":\"Red\",\"strokeWidth\":3,\"name\":\"5\",\"draggable\":true,\"visible\":false},\"className\":\"Image\"}",
				"sugg_img": "{\"attrs\":{\"x\":209,\"y\":301,\"width\":70,\"height\":70,\"strokeEnabled\":false,\"stroke\":\"Red\",\"strokeWidth\":3,\"name\":\"5\",\"draggable\":true,\"visible\":false},\"className\":\"Image\"}"
			}
		},
		"7": {
			"1": {
				"loaded": true,
				"resizing": false,
				"fixed": false,
				"align_type": -1,
				"num_lines": 1,
				"selected": false,
				"old_text": "",
				"type": "text",
				"id": 7,
				"fixed_amount": 0.8359729153291425,
				"alternate_id": 0,
				"x": 228,
				"y": 89,
				"group_id": "-1",
				"importance": "2",
				"type_id": 1,
				"font": "Garamond",
				"bold": false,
				"italic": false,
				"fix_alignment": false,
				"fix_alternate": false,
				"color": "FF0000",
				"text": "Winner of the Killan Prize",
				"align": "center",
				"sugg_align": "left",
				"height": 33,
				"orig_text": "Winner of the\nKillan Prize",
				"max_line_length": 26,
				"alignment_imgs": {
					"left": "{\"attrs\":{\"x\":228,\"y\":89,\"width\":339.90000000000003,\"height\":33,\"strokeEnabled\":false,\"stroke\":\"Red\",\"strokeWidth\":3,\"name\":\"7\",\"draggable\":true,\"visible\":true,\"opacity\":1,\"rotation\":0,\"scaleX\":1,\"scaleY\":1,\"offsetX\":0,\"offsetY\":0,\"skewX\":0,\"skewY\":0},\"className\":\"Image\"}"
				},
				"alignment_sugg_imgs": {
					"left": "{\"attrs\":{\"x\":222,\"y\":89,\"width\":350.20000000000005,\"height\":34,\"strokeEnabled\":false,\"stroke\":\"Red\",\"strokeWidth\":3,\"name\":\"7\",\"draggable\":true,\"visible\":true},\"className\":\"Image\"}"
				},
				"anchors": {
					"topLeft": "{\"attrs\":{\"x\":228,\"y\":122,\"fill\":\"#292\",\"opacity\":0.6,\"radius\":6,\"name\":\"topLeft\",\"draggable\":true,\"visible\":false},\"className\":\"Circle\"}",
					"topRight": "{\"attrs\":{\"x\":567.9000000000001,\"y\":122,\"fill\":\"#292\",\"opacity\":0.6,\"radius\":6,\"name\":\"topRight\",\"draggable\":true,\"visible\":false},\"className\":\"Circle\"}",
					"bottomLeft": "{\"attrs\":{\"x\":228,\"y\":89,\"fill\":\"#292\",\"opacity\":0.6,\"radius\":6,\"name\":\"bottomLeft\",\"draggable\":true,\"visible\":false},\"className\":\"Circle\"}",
					"bottomRight": "{\"attrs\":{\"x\":567.9000000000001,\"y\":89,\"fill\":\"#292\",\"opacity\":0.6,\"radius\":6,\"name\":\"bottomRight\",\"draggable\":true,\"visible\":false},\"className\":\"Circle\"}"
				},
				"aspect_ratio": 10.3,
				"curr_pos": {
					"x": 388.111083984375,
					"y": 107
				},
				"width": 339.90000000000003,
				"region_id": -1,
				"img": "{\"attrs\":{\"x\":228,\"y\":89,\"width\":339.90000000000003,\"height\":33,\"strokeEnabled\":false,\"stroke\":\"Red\",\"strokeWidth\":3,\"name\":\"7\",\"draggable\":true,\"visible\":true,\"opacity\":1,\"rotation\":0,\"scaleX\":1,\"scaleY\":1,\"offsetX\":0,\"offsetY\":0,\"skewX\":0,\"skewY\":0},\"className\":\"Image\"}",
				"sugg_img": "{\"attrs\":{\"x\":222,\"y\":89,\"width\":350.20000000000005,\"height\":34,\"strokeEnabled\":false,\"stroke\":\"Red\",\"strokeWidth\":3,\"name\":\"7\",\"draggable\":true,\"visible\":true},\"className\":\"Image\"}"
			},
			"2": {
				"loaded": true,
				"resizing": false,
				"fixed": false,
				"align_type": 1,
				"num_lines": 2,
				"selected": true,
				"old_text": "",
				"type": "text",
				"id": 7,
				"fixed_amount": 0.4380502949036002,
				"alternate_id": 1,
				"x": 255,
				"y": 84,
				"group_id": "-1",
				"importance": "2",
				"type_id": 1,
				"font": "Garamond",
				"bold": false,
				"italic": false,
				"fix_alignment": false,
				"fix_alternate": false,
				"color": "FF0000",
				"text": "Winner of the\nKillan Prize",
				"align": "center",
				"sugg_align": "center",
				"height": 55,
				"orig_text": "Winner of the\nKillan Prize",
				"max_line_length": 13,
				"alignment_imgs": {
					"left": "{\"attrs\":{\"x\":15,\"y\":61,\"width\":182.01666666666668,\"height\":67,\"strokeEnabled\":false,\"stroke\":\"Red\",\"strokeWidth\":3,\"name\":\"7\",\"draggable\":true,\"visible\":true,\"opacity\":1},\"className\":\"Image\"}",
					"center": "{\"attrs\":{\"x\":255,\"y\":84,\"width\":149.41666666666669,\"height\":55,\"strokeEnabled\":true,\"stroke\":\"Red\",\"strokeWidth\":3,\"name\":\"7\",\"draggable\":true,\"visible\":true,\"opacity\":1,\"rotation\":0,\"scaleX\":1,\"scaleY\":1,\"offsetX\":0,\"offsetY\":0,\"skewX\":0,\"skewY\":0},\"className\":\"Image\"}",
					"right": "{\"attrs\":{\"x\":210,\"y\":211,\"width\":165.71666666666667,\"height\":61,\"strokeEnabled\":false,\"stroke\":\"Red\",\"strokeWidth\":3,\"name\":\"7\",\"draggable\":true,\"visible\":false},\"className\":\"Image\"}"
				},
				"alignment_sugg_imgs": {
					"left": "{\"attrs\":{\"x\":346,\"y\":171,\"width\":190.16666666666669,\"height\":70,\"strokeEnabled\":false,\"stroke\":\"Red\",\"strokeWidth\":3,\"name\":\"7\",\"draggable\":true,\"visible\":true},\"className\":\"Image\"}",
					"center": "{\"attrs\":{\"x\":362,\"y\":113,\"width\":190.16666666666669,\"height\":70,\"strokeEnabled\":false,\"stroke\":\"Red\",\"strokeWidth\":3,\"name\":\"7\",\"draggable\":true,\"visible\":true},\"className\":\"Image\"}",
					"right": "{\"attrs\":{\"x\":210,\"y\":211,\"width\":165.71666666666667,\"height\":61,\"strokeEnabled\":false,\"stroke\":\"Red\",\"strokeWidth\":3,\"name\":\"7\",\"draggable\":true,\"visible\":false},\"className\":\"Image\"}"
				},
				"anchors": {
					"topLeft": "{\"attrs\":{\"x\":255,\"y\":139,\"fill\":\"#292\",\"opacity\":0.6,\"radius\":6,\"name\":\"topLeft\",\"draggable\":true,\"visible\":false},\"className\":\"Circle\"}",
					"topRight": "{\"attrs\":{\"x\":404.4166666666667,\"y\":139,\"fill\":\"#292\",\"opacity\":0.6,\"radius\":6,\"name\":\"topRight\",\"draggable\":true,\"visible\":false,\"rotation\":0,\"scaleX\":1,\"scaleY\":1,\"offsetX\":0,\"offsetY\":0,\"skewX\":0,\"skewY\":0},\"className\":\"Circle\"}",
					"bottomLeft": "{\"attrs\":{\"x\":255,\"y\":84,\"fill\":\"#292\",\"opacity\":0.6,\"radius\":6,\"name\":\"bottomLeft\",\"draggable\":true,\"visible\":false},\"className\":\"Circle\"}",
					"bottomRight": "{\"attrs\":{\"x\":404.4166666666667,\"y\":84,\"fill\":\"#292\",\"opacity\":0.6,\"radius\":6,\"name\":\"bottomRight\",\"draggable\":true,\"visible\":false},\"className\":\"Circle\"}"
				},
				"aspect_ratio": 2.716666666666667,
				"curr_pos": {
					"x": 338.111083984375,
					"y": 123
				},
				"width": 198.31666666666666,
				"region_id": -1,
				"img": "{\"attrs\":{\"x\":255,\"y\":84,\"width\":149.41666666666669,\"height\":55,\"strokeEnabled\":true,\"stroke\":\"Red\",\"strokeWidth\":3,\"name\":\"7\",\"draggable\":true,\"visible\":true,\"opacity\":1,\"rotation\":0,\"scaleX\":1,\"scaleY\":1,\"offsetX\":0,\"offsetY\":0,\"skewX\":0,\"skewY\":0},\"className\":\"Image\"}",
				"sugg_img": "{\"attrs\":{\"x\":362,\"y\":113,\"width\":190.16666666666669,\"height\":70,\"strokeEnabled\":false,\"stroke\":\"Red\",\"strokeWidth\":3,\"name\":\"7\",\"draggable\":true,\"visible\":true},\"className\":\"Image\"}"
			},
			"3": {
				"loaded": true,
				"resizing": false,
				"fixed": false,
				"align_type": -1,
				"num_lines": 3,
				"selected": false,
				"old_text": "",
				"type": "text",
				"id": 7,
				"fixed_amount": 0.25,
				"alternate_id": 2,
				"x": 210,
				"y": 211,
				"group_id": "-1",
				"importance": "2",
				"type_id": 1,
				"font": "Garamond",
				"bold": false,
				"italic": false,
				"fix_alignment": false,
				"fix_alternate": false,
				"color": "FF0000",
				"text": "Winner of\nthe Killan\nPrize",
				"align": "left",
				"sugg_align": "left",
				"height": 61,
				"orig_text": "Winner of the\nKillan Prize",
				"max_line_length": 10,
				"alignment_imgs": {
					"left": "{\"attrs\":{\"x\":210,\"y\":211,\"width\":80.17142857142858,\"height\":61,\"strokeEnabled\":false,\"stroke\":\"Red\",\"strokeWidth\":3,\"name\":\"7\",\"draggable\":true,\"visible\":false},\"className\":\"Image\"}",
					"center": "{\"attrs\":{\"x\":210,\"y\":211,\"width\":80.17142857142858,\"height\":61,\"strokeEnabled\":false,\"stroke\":\"Red\",\"strokeWidth\":3,\"name\":\"7\",\"draggable\":true,\"visible\":false},\"className\":\"Image\"}",
					"right": "{\"attrs\":{\"x\":210,\"y\":211,\"width\":80.17142857142858,\"height\":61,\"strokeEnabled\":false,\"stroke\":\"Red\",\"strokeWidth\":3,\"name\":\"7\",\"draggable\":true,\"visible\":false},\"className\":\"Image\"}"
				},
				"alignment_sugg_imgs": {
					"left": "{\"attrs\":{\"x\":210,\"y\":211,\"width\":80.17142857142858,\"height\":61,\"strokeEnabled\":false,\"stroke\":\"Red\",\"strokeWidth\":3,\"name\":\"7\",\"draggable\":true,\"visible\":false},\"className\":\"Image\"}",
					"center": "{\"attrs\":{\"x\":210,\"y\":211,\"width\":80.17142857142858,\"height\":61,\"strokeEnabled\":false,\"stroke\":\"Red\",\"strokeWidth\":3,\"name\":\"7\",\"draggable\":true,\"visible\":false},\"className\":\"Image\"}",
					"right": "{\"attrs\":{\"x\":210,\"y\":211,\"width\":80.17142857142858,\"height\":61,\"strokeEnabled\":false,\"stroke\":\"Red\",\"strokeWidth\":3,\"name\":\"7\",\"draggable\":true,\"visible\":false},\"className\":\"Image\"}"
				},
				"anchors": {
					"topLeft": "{\"attrs\":{\"x\":0,\"y\":0,\"fill\":\"#292\",\"opacity\":0.6,\"radius\":6,\"name\":\"topLeft\",\"draggable\":true,\"visible\":false},\"className\":\"Circle\"}",
					"topRight": "{\"attrs\":{\"x\":0,\"y\":0,\"fill\":\"#292\",\"opacity\":0.6,\"radius\":6,\"name\":\"topRight\",\"draggable\":true,\"visible\":false},\"className\":\"Circle\"}",
					"bottomLeft": "{\"attrs\":{\"x\":0,\"y\":0,\"fill\":\"#292\",\"opacity\":0.6,\"radius\":6,\"name\":\"bottomLeft\",\"draggable\":true,\"visible\":false},\"className\":\"Circle\"}",
					"bottomRight": "{\"attrs\":{\"x\":0,\"y\":0,\"fill\":\"#292\",\"opacity\":0.6,\"radius\":6,\"name\":\"bottomRight\",\"draggable\":true,\"visible\":false},\"className\":\"Circle\"}"
				},
				"aspect_ratio": 1.3142857142857143,
				"curr_pos": {
					"x": 327.4444274902344,
					"y": 217
				},
				"width": 165.71666666666667,
				"region_id": -1,
				"img": "{\"attrs\":{\"x\":210,\"y\":211,\"width\":80.17142857142858,\"height\":61,\"strokeEnabled\":false,\"stroke\":\"Red\",\"strokeWidth\":3,\"name\":\"7\",\"draggable\":true,\"visible\":false},\"className\":\"Image\"}",
				"sugg_img": "{\"attrs\":{\"x\":210,\"y\":211,\"width\":80.17142857142858,\"height\":61,\"strokeEnabled\":false,\"stroke\":\"Red\",\"strokeWidth\":3,\"name\":\"7\",\"draggable\":true,\"visible\":false},\"className\":\"Image\"}"
			},
			"4": {
				"loaded": true,
				"resizing": false,
				"fixed": false,
				"align_type": -1,
				"num_lines": 4,
				"selected": false,
				"old_text": "",
				"type": "text",
				"id": 7,
				"fixed_amount": 0.25,
				"alternate_id": 3,
				"x": 210,
				"y": 211,
				"group_id": "-1",
				"importance": "2",
				"type_id": 1,
				"font": "Garamond",
				"bold": false,
				"italic": false,
				"fix_alignment": false,
				"fix_alternate": false,
				"color": "FF0000",
				"text": "Winner\nof the\nKillan\nPrize",
				"align": "left",
				"sugg_align": "left",
				"height": 61,
				"orig_text": "Winner of the\nKillan Prize",
				"max_line_length": 6,
				"alignment_imgs": {
					"left": "{\"attrs\":{\"x\":210,\"y\":211,\"width\":44.225,\"height\":61,\"strokeEnabled\":false,\"stroke\":\"Red\",\"strokeWidth\":3,\"name\":\"7\",\"draggable\":true,\"visible\":false},\"className\":\"Image\"}",
					"center": "{\"attrs\":{\"x\":210,\"y\":211,\"width\":44.225,\"height\":61,\"strokeEnabled\":false,\"stroke\":\"Red\",\"strokeWidth\":3,\"name\":\"7\",\"draggable\":true,\"visible\":false},\"className\":\"Image\"}",
					"right": "{\"attrs\":{\"x\":210,\"y\":211,\"width\":44.225,\"height\":61,\"strokeEnabled\":false,\"stroke\":\"Red\",\"strokeWidth\":3,\"name\":\"7\",\"draggable\":true,\"visible\":false},\"className\":\"Image\"}"
				},
				"alignment_sugg_imgs": {
					"left": "{\"attrs\":{\"x\":210,\"y\":211,\"width\":44.225,\"height\":61,\"strokeEnabled\":false,\"stroke\":\"Red\",\"strokeWidth\":3,\"name\":\"7\",\"draggable\":true,\"visible\":false},\"className\":\"Image\"}",
					"center": "{\"attrs\":{\"x\":210,\"y\":211,\"width\":44.225,\"height\":61,\"strokeEnabled\":false,\"stroke\":\"Red\",\"strokeWidth\":3,\"name\":\"7\",\"draggable\":true,\"visible\":false},\"className\":\"Image\"}",
					"right": "{\"attrs\":{\"x\":210,\"y\":211,\"width\":44.225,\"height\":61,\"strokeEnabled\":false,\"stroke\":\"Red\",\"strokeWidth\":3,\"name\":\"7\",\"draggable\":true,\"visible\":false},\"className\":\"Image\"}"
				},
				"anchors": {
					"topLeft": "{\"attrs\":{\"x\":0,\"y\":0,\"fill\":\"#292\",\"opacity\":0.6,\"radius\":6,\"name\":\"topLeft\",\"draggable\":true,\"visible\":false},\"className\":\"Circle\"}",
					"topRight": "{\"attrs\":{\"x\":0,\"y\":0,\"fill\":\"#292\",\"opacity\":0.6,\"radius\":6,\"name\":\"topRight\",\"draggable\":true,\"visible\":false},\"className\":\"Circle\"}",
					"bottomLeft": "{\"attrs\":{\"x\":0,\"y\":0,\"fill\":\"#292\",\"opacity\":0.6,\"radius\":6,\"name\":\"bottomLeft\",\"draggable\":true,\"visible\":false},\"className\":\"Circle\"}",
					"bottomRight": "{\"attrs\":{\"x\":0,\"y\":0,\"fill\":\"#292\",\"opacity\":0.6,\"radius\":6,\"name\":\"bottomRight\",\"draggable\":true,\"visible\":false},\"className\":\"Circle\"}"
				},
				"aspect_ratio": 0.725,
				"curr_pos": {
					"x": 327.4444274902344,
					"y": 217
				},
				"width": 165.71666666666667,
				"region_id": -1,
				"img": "{\"attrs\":{\"x\":210,\"y\":211,\"width\":44.225,\"height\":61,\"strokeEnabled\":false,\"stroke\":\"Red\",\"strokeWidth\":3,\"name\":\"7\",\"draggable\":true,\"visible\":false},\"className\":\"Image\"}",
				"sugg_img": "{\"attrs\":{\"x\":210,\"y\":211,\"width\":44.225,\"height\":61,\"strokeEnabled\":false,\"stroke\":\"Red\",\"strokeWidth\":3,\"name\":\"7\",\"draggable\":true,\"visible\":false},\"className\":\"Image\"}"
			},
			"5": {
				"loaded": true,
				"resizing": false,
				"fixed": false,
				"align_type": -1,
				"num_lines": 5,
				"selected": false,
				"old_text": "",
				"type": "text",
				"id": 7,
				"fixed_amount": 0.25,
				"alternate_id": 4,
				"x": 210,
				"y": 211,
				"group_id": "-1",
				"importance": "2",
				"type_id": 1,
				"font": "Garamond",
				"bold": false,
				"italic": false,
				"fix_alignment": false,
				"fix_alternate": false,
				"color": "FF0000",
				"text": "Winner\nof\nthe\nKillan\nPrize",
				"align": "left",
				"sugg_align": "left",
				"height": 61,
				"orig_text": "Winner of the\nKillan Prize",
				"max_line_length": 6,
				"alignment_imgs": {
					"left": "{\"attrs\":{\"x\":210,\"y\":211,\"width\":34.56666666666666,\"height\":61,\"strokeEnabled\":false,\"stroke\":\"Red\",\"strokeWidth\":3,\"name\":\"7\",\"draggable\":true,\"visible\":false},\"className\":\"Image\"}",
					"center": "{\"attrs\":{\"x\":210,\"y\":211,\"width\":34.56666666666666,\"height\":61,\"strokeEnabled\":false,\"stroke\":\"Red\",\"strokeWidth\":3,\"name\":\"7\",\"draggable\":true,\"visible\":false},\"className\":\"Image\"}",
					"right": "{\"attrs\":{\"x\":210,\"y\":211,\"width\":34.56666666666666,\"height\":61,\"strokeEnabled\":false,\"stroke\":\"Red\",\"strokeWidth\":3,\"name\":\"7\",\"draggable\":true,\"visible\":false},\"className\":\"Image\"}"
				},
				"alignment_sugg_imgs": {
					"left": "{\"attrs\":{\"x\":210,\"y\":211,\"width\":34.56666666666666,\"height\":61,\"strokeEnabled\":false,\"stroke\":\"Red\",\"strokeWidth\":3,\"name\":\"7\",\"draggable\":true,\"visible\":false},\"className\":\"Image\"}",
					"center": "{\"attrs\":{\"x\":210,\"y\":211,\"width\":34.56666666666666,\"height\":61,\"strokeEnabled\":false,\"stroke\":\"Red\",\"strokeWidth\":3,\"name\":\"7\",\"draggable\":true,\"visible\":false},\"className\":\"Image\"}",
					"right": "{\"attrs\":{\"x\":210,\"y\":211,\"width\":34.56666666666666,\"height\":61,\"strokeEnabled\":false,\"stroke\":\"Red\",\"strokeWidth\":3,\"name\":\"7\",\"draggable\":true,\"visible\":false},\"className\":\"Image\"}"
				},
				"anchors": {
					"topLeft": "{\"attrs\":{\"x\":0,\"y\":0,\"fill\":\"#292\",\"opacity\":0.6,\"radius\":6,\"name\":\"topLeft\",\"draggable\":true,\"visible\":false},\"className\":\"Circle\"}",
					"topRight": "{\"attrs\":{\"x\":0,\"y\":0,\"fill\":\"#292\",\"opacity\":0.6,\"radius\":6,\"name\":\"topRight\",\"draggable\":true,\"visible\":false},\"className\":\"Circle\"}",
					"bottomLeft": "{\"attrs\":{\"x\":0,\"y\":0,\"fill\":\"#292\",\"opacity\":0.6,\"radius\":6,\"name\":\"bottomLeft\",\"draggable\":true,\"visible\":false},\"className\":\"Circle\"}",
					"bottomRight": "{\"attrs\":{\"x\":0,\"y\":0,\"fill\":\"#292\",\"opacity\":0.6,\"radius\":6,\"name\":\"bottomRight\",\"draggable\":true,\"visible\":false},\"className\":\"Circle\"}"
				},
				"aspect_ratio": 0.5666666666666667,
				"curr_pos": {
					"x": 327.4444274902344,
					"y": 217
				},
				"width": 165.71666666666667,
				"region_id": -1,
				"img": "{\"attrs\":{\"x\":210,\"y\":211,\"width\":34.56666666666666,\"height\":61,\"strokeEnabled\":false,\"stroke\":\"Red\",\"strokeWidth\":3,\"name\":\"7\",\"draggable\":true,\"visible\":false},\"className\":\"Image\"}",
				"sugg_img": "{\"attrs\":{\"x\":210,\"y\":211,\"width\":34.56666666666666,\"height\":61,\"strokeEnabled\":false,\"stroke\":\"Red\",\"strokeWidth\":3,\"name\":\"7\",\"draggable\":true,\"visible\":false},\"className\":\"Image\"}"
			}
		}
	},
	"region_proposals": false
}